{"atlas":{"frames":{"acc_head_U_starearrings_h_std_he_3714_3_0.png":{"frame":{"x":0,"y":0,"w":26,"h":11},"rotated":false,"trimmed":false,"spriteSourceSize":{"x":0,"y":0,"w":26,"h":11},"sourceSize":{"w":26,"h":11},"pivot":{"x":0.5,"y":0.5}},"acc_head_U_starearrings_h_std_he_3714_0_0.png":{"frame":{"x":26,"y":0,"w":10,"h":12},"rotated":false,"trimmed":false,"spriteSourceSize":{"x":0,"y":0,"w":10,"h":12},"sourceSize":{"w":10,"h":12},"pivot":{"x":0.5,"y":0.5}},"acc_head_U_starearrings_h_lay_he_3714_2_0.png":{"frame":{"x":0,"y":11,"w":10,"h":11},"rotated":false,"trimmed":false,"spriteSourceSize":{"x":0,"y":0,"w":10,"h":11},"sourceSize":{"w":10,"h":11},"pivot":{"x":0.5,"y":0.5}},"acc_head_U_starearrings_h_std_he_3714_1_0.png":{"frame":{"x":26,"y":0,"w":10,"h":12},"rotated":false,"trimmed":false,"spriteSourceSize":{"x":0,"y":0,"w":10,"h":12},"sourceSize":{"w":10,"h":12},"pivot":{"x":0.5,"y":0.5}},"acc_head_U_starearrings_h_std_he_3714_2_0.png":{"frame":{"x":26,"y":0,"w":10,"h":12},"rotated":false,"trimmed":false,"spriteSourceSize":{"x":0,"y":0,"w":10,"h":12},"sourceSize":{"w":10,"h":12},"pivot":{"x":0.5,"y":0.5}},"acc_head_U_starearrings_h_std_he_3714_7_0.png":{"frame":{"x":0,"y":0,"w":26,"h":11},"rotated":false,"trimmed":false,"spriteSourceSize":{"x":0,"y":0,"w":26,"h":11},"sourceSize":{"w":26,"h":11},"pivot":{"x":0.5,"y":0.5}}},"meta":{"app":"http://github.com/odrick/free-tex-packer-core","version":"0.3.2","image":"pack-result.png","format":"RGBA8888","size":{"w":36,"h":22},"scale":1}},"h_lay_he_3714_2_0":{"x":12,"y":18,"exists":true},"h_std_he_3714_7_0":{"x":-20,"y":54,"exists":true},"h_std_he_3714_3_0":{"x":-20,"y":56,"exists":true},"h_std_he_3714_2_0":{"x":-20,"y":56,"exists":true},"h_std_he_3714_1_0":{"x":-24,"y":54,"exists":true},"h_std_he_3714_0_0":{"x":-35,"y":54,"exists":true}}