{"atlas":{"frames":{"jacket_M_raincoat_h_std_cc_3500_7_0.png":{"frame":{"x":0,"y":0,"w":72,"h":120},"rotated":false,"trimmed":false,"spriteSourceSize":{"x":0,"y":0,"w":72,"h":120},"sourceSize":{"w":72,"h":120},"pivot":{"x":0.5,"y":0.5}},"jacket_M_raincoat_h_crr_rc_3498_0_0.png":{"frame":{"x":0,"y":120,"w":32,"h":109},"rotated":false,"trimmed":false,"spriteSourceSize":{"x":0,"y":0,"w":32,"h":109},"sourceSize":{"w":32,"h":109},"pivot":{"x":0.5,"y":0.5}},"jacket_M_raincoat_h_std_cc_3498_2_0.png":{"frame":{"x":0,"y":229,"w":31,"h":45},"rotated":false,"trimmed":false,"spriteSourceSize":{"x":0,"y":0,"w":31,"h":45},"sourceSize":{"w":31,"h":45},"pivot":{"x":0.5,"y":0.5}},"jacket_M_raincoat_h_std_cc_3498_3_0.png":{"frame":{"x":0,"y":274,"w":29,"h":40},"rotated":false,"trimmed":false,"spriteSourceSize":{"x":0,"y":0,"w":29,"h":40},"sourceSize":{"w":29,"h":40},"pivot":{"x":0.5,"y":0.5}},"jacket_M_raincoat_h_std_cc_3498_0_0.png":{"frame":{"x":0,"y":314,"w":28,"h":40},"rotated":false,"trimmed":false,"spriteSourceSize":{"x":0,"y":0,"w":28,"h":40},"sourceSize":{"w":28,"h":40},"pivot":{"x":0.5,"y":0.5}},"jacket_M_raincoat_h_std_cc_3498_7_0.png":{"frame":{"x":0,"y":354,"w":25,"h":37},"rotated":false,"trimmed":false,"spriteSourceSize":{"x":0,"y":0,"w":25,"h":37},"sourceSize":{"w":25,"h":37},"pivot":{"x":0.5,"y":0.5}},"jacket_M_raincoat_h_std_cc_3498_1_0.png":{"frame":{"x":0,"y":391,"w":25,"h":35},"rotated":false,"trimmed":false,"spriteSourceSize":{"x":0,"y":0,"w":25,"h":35},"sourceSize":{"w":25,"h":35},"pivot":{"x":0.5,"y":0.5}},"jacket_M_raincoat_h_std_cc_3500_0_0.png":{"frame":{"x":0,"y":426,"w":25,"h":35},"rotated":false,"trimmed":false,"spriteSourceSize":{"x":0,"y":0,"w":25,"h":35},"sourceSize":{"w":25,"h":35},"pivot":{"x":0.5,"y":0.5}},"jacket_M_raincoat_h_std_cc_3500_2_0.png":{"frame":{"x":0,"y":461,"w":29,"h":33},"rotated":false,"trimmed":false,"spriteSourceSize":{"x":0,"y":0,"w":29,"h":33},"sourceSize":{"w":29,"h":33},"pivot":{"x":0.5,"y":0.5}},"jacket_M_raincoat_h_wlk_rc_3498_2_3.png":{"frame":{"x":25,"y":354,"w":17,"h":33},"rotated":false,"trimmed":false,"spriteSourceSize":{"x":0,"y":0,"w":17,"h":33},"sourceSize":{"w":17,"h":33},"pivot":{"x":0.5,"y":0.5}},"jacket_M_raincoat_h_lay_cc_3498_2_0.png":{"frame":{"x":28,"y":314,"w":57,"h":32},"rotated":false,"trimmed":false,"spriteSourceSize":{"x":0,"y":0,"w":57,"h":32},"sourceSize":{"w":57,"h":32},"pivot":{"x":0.5,"y":0.5}},"jacket_M_raincoat_h_wlk_lc_3500_7_1.png":{"frame":{"x":28,"y":346,"w":5,"h":8},"rotated":false,"trimmed":false,"spriteSourceSize":{"x":0,"y":0,"w":5,"h":8},"sourceSize":{"w":5,"h":8},"pivot":{"x":0.5,"y":0.5}},"jacket_M_raincoat_h_wlk_rc_3500_7_3.png":{"frame":{"x":33,"y":346,"w":5,"h":8},"rotated":false,"trimmed":false,"spriteSourceSize":{"x":0,"y":0,"w":5,"h":8},"sourceSize":{"w":5,"h":8},"pivot":{"x":0.5,"y":0.5}},"jacket_M_raincoat_h_drk_rc_3500_6_0.png":{"frame":{"x":38,"y":346,"w":21,"h":7},"rotated":false,"trimmed":false,"spriteSourceSize":{"x":0,"y":0,"w":21,"h":7},"sourceSize":{"w":21,"h":7},"pivot":{"x":0.5,"y":0.5}},"jacket_M_raincoat_h_crr_lc_3499_0_0.png":{"frame":{"x":38,"y":353,"w":1,"h":1},"rotated":false,"trimmed":false,"spriteSourceSize":{"x":0,"y":0,"w":1,"h":1},"sourceSize":{"w":1,"h":1},"pivot":{"x":0.5,"y":0.5}},"jacket_M_raincoat_h_crr_lc_3500_0_0.png":{"frame":{"x":39,"y":353,"w":1,"h":1},"rotated":false,"trimmed":false,"spriteSourceSize":{"x":0,"y":0,"w":1,"h":1},"sourceSize":{"w":1,"h":1},"pivot":{"x":0.5,"y":0.5}},"jacket_M_raincoat_h_std_cc_3499_0_0.png":{"frame":{"x":40,"y":353,"w":1,"h":1},"rotated":false,"trimmed":false,"spriteSourceSize":{"x":0,"y":0,"w":1,"h":1},"sourceSize":{"w":1,"h":1},"pivot":{"x":0.5,"y":0.5}},"jacket_M_raincoat_h_wlk_lc_3500_0_0.png":{"frame":{"x":41,"y":353,"w":1,"h":1},"rotated":false,"trimmed":false,"spriteSourceSize":{"x":0,"y":0,"w":1,"h":1},"sourceSize":{"w":1,"h":1},"pivot":{"x":0.5,"y":0.5}},"jacket_M_raincoat_h_std_rc_3498_2_0.png":{"frame":{"x":29,"y":274,"w":17,"h":32},"rotated":false,"trimmed":false,"spriteSourceSize":{"x":0,"y":0,"w":17,"h":32},"sourceSize":{"w":17,"h":32},"pivot":{"x":0.5,"y":0.5}},"jacket_M_raincoat_h_drk_rc_3500_7_0.png":{"frame":{"x":29,"y":306,"w":5,"h":5},"rotated":false,"trimmed":false,"spriteSourceSize":{"x":0,"y":0,"w":5,"h":5},"sourceSize":{"w":5,"h":5},"pivot":{"x":0.5,"y":0.5}},"jacket_M_raincoat_h_std_lc_3500_0_0.png":{"frame":{"x":29,"y":311,"w":2,"h":2},"rotated":false,"trimmed":false,"spriteSourceSize":{"x":0,"y":0,"w":2,"h":2},"sourceSize":{"w":2,"h":2},"pivot":{"x":0.5,"y":0.5}},"jacket_M_raincoat_h_wlk_lc_3500_1_3.png":{"frame":{"x":29,"y":313,"w":1,"h":1},"rotated":false,"trimmed":false,"spriteSourceSize":{"x":0,"y":0,"w":1,"h":1},"sourceSize":{"w":1,"h":1},"pivot":{"x":0.5,"y":0.5}},"jacket_M_raincoat_h_wlk_lc_3500_2_3.png":{"frame":{"x":31,"y":311,"w":2,"h":2},"rotated":false,"trimmed":false,"spriteSourceSize":{"x":0,"y":0,"w":2,"h":2},"sourceSize":{"w":2,"h":2},"pivot":{"x":0.5,"y":0.5}},"jacket_M_raincoat_h_wav_lc_3499_2_0.png":{"frame":{"x":33,"y":311,"w":1,"h":2},"rotated":false,"trimmed":false,"spriteSourceSize":{"x":0,"y":0,"w":1,"h":2},"sourceSize":{"w":1,"h":2},"pivot":{"x":0.5,"y":0.5}},"jacket_M_raincoat_h_wlk_rc_3498_2_1.png":{"frame":{"x":31,"y":229,"w":15,"h":32},"rotated":false,"trimmed":false,"spriteSourceSize":{"x":0,"y":0,"w":15,"h":32},"sourceSize":{"w":15,"h":32},"pivot":{"x":0.5,"y":0.5}},"jacket_M_raincoat_h_drk_rc_3498_6_0.png":{"frame":{"x":31,"y":261,"w":28,"h":13},"rotated":false,"trimmed":false,"spriteSourceSize":{"x":0,"y":0,"w":28,"h":13},"sourceSize":{"w":28,"h":13},"pivot":{"x":0.5,"y":0.5}},"jacket_M_raincoat_h_crr_lc_3498_4_0.png":{"frame":{"x":46,"y":274,"w":20,"h":31},"rotated":false,"trimmed":false,"spriteSourceSize":{"x":0,"y":0,"w":20,"h":31},"sourceSize":{"w":20,"h":31},"pivot":{"x":0.5,"y":0.5}},"jacket_M_raincoat_h_crr_rc_3498_2_0.png":{"frame":{"x":25,"y":387,"w":20,"h":31},"rotated":false,"trimmed":false,"spriteSourceSize":{"x":0,"y":0,"w":20,"h":31},"sourceSize":{"w":20,"h":31},"pivot":{"x":0.5,"y":0.5}},"jacket_M_raincoat_h_std_cc_3500_3_0.png":{"frame":{"x":42,"y":353,"w":27,"h":30},"rotated":false,"trimmed":false,"spriteSourceSize":{"x":0,"y":0,"w":27,"h":30},"sourceSize":{"w":27,"h":30},"pivot":{"x":0.5,"y":0.5}},"jacket_M_raincoat_h_wav_lc_3498_6_0.png":{"frame":{"x":25,"y":418,"w":21,"h":30},"rotated":false,"trimmed":false,"spriteSourceSize":{"x":0,"y":0,"w":21,"h":30},"sourceSize":{"w":21,"h":30},"pivot":{"x":0.5,"y":0.5}},"jacket_M_raincoat_h_std_cc_3500_1_0.png":{"frame":{"x":25,"y":448,"w":22,"h":13},"rotated":false,"trimmed":false,"spriteSourceSize":{"x":0,"y":0,"w":22,"h":13},"sourceSize":{"w":22,"h":13},"pivot":{"x":0.5,"y":0.5}},"jacket_M_raincoat_h_wav_lc_3498_5_0.png":{"frame":{"x":45,"y":383,"w":17,"h":30},"rotated":false,"trimmed":false,"spriteSourceSize":{"x":0,"y":0,"w":17,"h":30},"sourceSize":{"w":17,"h":30},"pivot":{"x":0.5,"y":0.5}},"jacket_M_raincoat_h_wav_lc_3498_6_1.png":{"frame":{"x":46,"y":413,"w":24,"h":29},"rotated":false,"trimmed":false,"spriteSourceSize":{"x":0,"y":0,"w":24,"h":29},"sourceSize":{"w":24,"h":29},"pivot":{"x":0.5,"y":0.5}},"jacket_M_raincoat_h_wav_lc_3498_7_1.png":{"frame":{"x":62,"y":383,"w":19,"h":29},"rotated":false,"trimmed":false,"spriteSourceSize":{"x":0,"y":0,"w":19,"h":29},"sourceSize":{"w":19,"h":29},"pivot":{"x":0.5,"y":0.5}},"jacket_M_raincoat_h_wav_lc_3498_7_0.png":{"frame":{"x":69,"y":346,"w":17,"h":29},"rotated":false,"trimmed":false,"spriteSourceSize":{"x":0,"y":0,"w":17,"h":29},"sourceSize":{"w":17,"h":29},"pivot":{"x":0.5,"y":0.5}},"jacket_M_raincoat_h_std_rc_3500_2_0.png":{"frame":{"x":81,"y":375,"w":16,"h":29},"rotated":false,"trimmed":false,"spriteSourceSize":{"x":0,"y":0,"w":16,"h":29},"sourceSize":{"w":16,"h":29},"pivot":{"x":0.5,"y":0.5}},"jacket_M_raincoat_h_wav_lc_3498_2_0.png":{"frame":{"x":32,"y":120,"w":16,"h":29},"rotated":false,"trimmed":false,"spriteSourceSize":{"x":0,"y":0,"w":16,"h":29},"sourceSize":{"w":16,"h":29},"pivot":{"x":0.5,"y":0.5}},"jacket_M_raincoat_h_wav_lc_3498_5_1.png":{"frame":{"x":32,"y":149,"w":16,"h":29},"rotated":false,"trimmed":false,"spriteSourceSize":{"x":0,"y":0,"w":16,"h":29},"sourceSize":{"w":16,"h":29},"pivot":{"x":0.5,"y":0.5}},"jacket_M_raincoat_h_wlk_rc_3500_2_0.png":{"frame":{"x":32,"y":178,"w":16,"h":29},"rotated":false,"trimmed":false,"spriteSourceSize":{"x":0,"y":0,"w":16,"h":29},"sourceSize":{"w":16,"h":29},"pivot":{"x":0.5,"y":0.5}},"jacket_M_raincoat_h_drk_rc_3498_2_0.png":{"frame":{"x":32,"y":207,"w":32,"h":22},"rotated":false,"trimmed":false,"spriteSourceSize":{"x":0,"y":0,"w":32,"h":22},"sourceSize":{"w":32,"h":22},"pivot":{"x":0.5,"y":0.5}},"jacket_M_raincoat_h_wav_lc_3500_6_0.png":{"frame":{"x":64,"y":207,"w":19,"h":22},"rotated":false,"trimmed":false,"spriteSourceSize":{"x":0,"y":0,"w":19,"h":22},"sourceSize":{"w":19,"h":22},"pivot":{"x":0.5,"y":0.5}},"jacket_M_raincoat_h_drk_rc_3498_3_0.png":{"frame":{"x":83,"y":207,"w":18,"h":22},"rotated":false,"trimmed":false,"spriteSourceSize":{"x":0,"y":0,"w":18,"h":22},"sourceSize":{"w":18,"h":22},"pivot":{"x":0.5,"y":0.5}},"jacket_M_raincoat_h_wlk_rc_3500_2_3.png":{"frame":{"x":46,"y":229,"w":16,"h":29},"rotated":false,"trimmed":false,"spriteSourceSize":{"x":0,"y":0,"w":16,"h":29},"sourceSize":{"w":16,"h":29},"pivot":{"x":0.5,"y":0.5}},"jacket_M_raincoat_h_drk_rc_3498_1_0.png":{"frame":{"x":59,"y":258,"w":28,"h":16},"rotated":false,"trimmed":false,"spriteSourceSize":{"x":0,"y":0,"w":28,"h":16},"sourceSize":{"w":28,"h":16},"pivot":{"x":0.5,"y":0.5}},"jacket_M_raincoat_h_wlk_rc_3500_2_1.png":{"frame":{"x":62,"y":229,"w":13,"h":29},"rotated":false,"trimmed":false,"spriteSourceSize":{"x":0,"y":0,"w":13,"h":29},"sourceSize":{"w":13,"h":29},"pivot":{"x":0.5,"y":0.5}},"jacket_M_raincoat_h_std_cc_3499_2_0.png":{"frame":{"x":75,"y":229,"w":11,"h":29},"rotated":false,"trimmed":false,"spriteSourceSize":{"x":0,"y":0,"w":11,"h":29},"sourceSize":{"w":11,"h":29},"pivot":{"x":0.5,"y":0.5}},"jacket_M_raincoat_h_std_lc_3498_3_0.png":{"frame":{"x":86,"y":229,"w":10,"h":29},"rotated":false,"trimmed":false,"spriteSourceSize":{"x":0,"y":0,"w":10,"h":29},"sourceSize":{"w":10,"h":29},"pivot":{"x":0.5,"y":0.5}},"jacket_M_raincoat_h_wlk_lc_3498_3_2.png":{"frame":{"x":66,"y":274,"w":10,"h":29},"rotated":false,"trimmed":false,"spriteSourceSize":{"x":0,"y":0,"w":10,"h":29},"sourceSize":{"w":10,"h":29},"pivot":{"x":0.5,"y":0.5}},"jacket_M_raincoat_h_drk_rc_3500_1_0.png":{"frame":{"x":66,"y":303,"w":25,"h":11},"rotated":false,"trimmed":false,"spriteSourceSize":{"x":0,"y":0,"w":25,"h":11},"sourceSize":{"w":25,"h":11},"pivot":{"x":0.5,"y":0.5}},"jacket_M_raincoat_h_wav_lc_3498_1_0.png":{"frame":{"x":86,"y":274,"w":85,"h":28},"rotated":false,"trimmed":false,"spriteSourceSize":{"x":0,"y":0,"w":85,"h":28},"sourceSize":{"w":85,"h":28},"pivot":{"x":0.5,"y":0.5}},"jacket_M_raincoat_h_std_rc_3498_3_0.png":{"frame":{"x":76,"y":274,"w":10,"h":28},"rotated":false,"trimmed":false,"spriteSourceSize":{"x":0,"y":0,"w":10,"h":28},"sourceSize":{"w":10,"h":28},"pivot":{"x":0.5,"y":0.5}},"jacket_M_raincoat_h_drk_rc_3498_5_0.png":{"frame":{"x":87,"y":258,"w":28,"h":16},"rotated":false,"trimmed":false,"spriteSourceSize":{"x":0,"y":0,"w":28,"h":16},"sourceSize":{"w":28,"h":16},"pivot":{"x":0.5,"y":0.5}},"jacket_M_raincoat_h_lay_cc_3499_2_0.png":{"frame":{"x":115,"y":258,"w":28,"h":16},"rotated":false,"trimmed":false,"spriteSourceSize":{"x":0,"y":0,"w":28,"h":16},"sourceSize":{"w":28,"h":16},"pivot":{"x":0.5,"y":0.5}},"jacket_M_raincoat_h_wav_lc_3498_1_1.png":{"frame":{"x":96,"y":229,"w":18,"h":28},"rotated":false,"trimmed":false,"spriteSourceSize":{"x":0,"y":0,"w":18,"h":28},"sourceSize":{"w":18,"h":28},"pivot":{"x":0.5,"y":0.5}},"jacket_M_raincoat_h_wav_lc_3498_2_1.png":{"frame":{"x":114,"y":229,"w":18,"h":28},"rotated":false,"trimmed":false,"spriteSourceSize":{"x":0,"y":0,"w":18,"h":28},"sourceSize":{"w":18,"h":28},"pivot":{"x":0.5,"y":0.5}},"jacket_M_raincoat_h_wav_lc_3498_3_1.png":{"frame":{"x":85,"y":314,"w":18,"h":28},"rotated":false,"trimmed":false,"spriteSourceSize":{"x":0,"y":0,"w":18,"h":28},"sourceSize":{"w":18,"h":28},"pivot":{"x":0.5,"y":0.5}},"jacket_M_raincoat_h_drk_rc_3500_5_0.png":{"frame":{"x":97,"y":302,"w":25,"h":11},"rotated":false,"trimmed":false,"spriteSourceSize":{"x":0,"y":0,"w":25,"h":11},"sourceSize":{"w":25,"h":11},"pivot":{"x":0.5,"y":0.5}},"jacket_M_raincoat_h_wav_lc_3498_3_0.png":{"frame":{"x":86,"y":342,"w":16,"h":28},"rotated":false,"trimmed":false,"spriteSourceSize":{"x":0,"y":0,"w":16,"h":28},"sourceSize":{"w":16,"h":28},"pivot":{"x":0.5,"y":0.5}},"jacket_M_raincoat_h_wav_lc_3498_0_0.png":{"frame":{"x":48,"y":120,"w":13,"h":28},"rotated":false,"trimmed":false,"spriteSourceSize":{"x":0,"y":0,"w":13,"h":28},"sourceSize":{"w":13,"h":28},"pivot":{"x":0.5,"y":0.5}},"jacket_M_raincoat_h_std_rc_3498_0_0.png":{"frame":{"x":48,"y":148,"w":12,"h":28},"rotated":false,"trimmed":false,"spriteSourceSize":{"x":0,"y":0,"w":12,"h":28},"sourceSize":{"w":12,"h":28},"pivot":{"x":0.5,"y":0.5}},"jacket_M_raincoat_h_wlk_lc_3498_3_0.png":{"frame":{"x":48,"y":176,"w":10,"h":28},"rotated":false,"trimmed":false,"spriteSourceSize":{"x":0,"y":0,"w":10,"h":28},"sourceSize":{"w":10,"h":28},"pivot":{"x":0.5,"y":0.5}},"jacket_M_raincoat_h_wlk_lc_3498_3_1.png":{"frame":{"x":58,"y":176,"w":10,"h":28},"rotated":false,"trimmed":false,"spriteSourceSize":{"x":0,"y":0,"w":10,"h":28},"sourceSize":{"w":10,"h":28},"pivot":{"x":0.5,"y":0.5}},"jacket_M_raincoat_h_wlk_rc_3498_3_3.png":{"frame":{"x":60,"y":148,"w":10,"h":28},"rotated":false,"trimmed":false,"spriteSourceSize":{"x":0,"y":0,"w":10,"h":28},"sourceSize":{"w":10,"h":28},"pivot":{"x":0.5,"y":0.5}},"jacket_M_raincoat_h_crr_lc_3498_3_0.png":{"frame":{"x":68,"y":120,"w":71,"h":27},"rotated":false,"trimmed":false,"spriteSourceSize":{"x":0,"y":0,"w":71,"h":27},"sourceSize":{"w":71,"h":27},"pivot":{"x":0.5,"y":0.5}},"jacket_M_raincoat_h_wlk_lc_3500_3_1.png":{"frame":{"x":61,"y":120,"w":7,"h":26},"rotated":false,"trimmed":false,"spriteSourceSize":{"x":0,"y":0,"w":7,"h":26},"sourceSize":{"w":7,"h":26},"pivot":{"x":0.5,"y":0.5}},"jacket_M_raincoat_h_wav_lc_3498_4_0.png":{"frame":{"x":68,"y":176,"w":26,"h":27},"rotated":false,"trimmed":false,"spriteSourceSize":{"x":0,"y":0,"w":26,"h":27},"sourceSize":{"w":26,"h":27},"pivot":{"x":0.5,"y":0.5}},"jacket_M_raincoat_h_wav_lc_3498_0_1.png":{"frame":{"x":70,"y":147,"w":16,"h":27},"rotated":false,"trimmed":false,"spriteSourceSize":{"x":0,"y":0,"w":16,"h":27},"sourceSize":{"w":16,"h":27},"pivot":{"x":0.5,"y":0.5}},"jacket_M_raincoat_h_std_cc_3499_3_0.png":{"frame":{"x":86,"y":147,"w":13,"h":27},"rotated":false,"trimmed":false,"spriteSourceSize":{"x":0,"y":0,"w":13,"h":27},"sourceSize":{"w":13,"h":27},"pivot":{"x":0.5,"y":0.5}},"jacket_M_raincoat_h_crr_rc_3498_3_0.png":{"frame":{"x":94,"y":174,"w":12,"h":27},"rotated":false,"trimmed":false,"spriteSourceSize":{"x":0,"y":0,"w":12,"h":27},"sourceSize":{"w":12,"h":27},"pivot":{"x":0.5,"y":0.5}},"jacket_M_raincoat_h_wlk_rc_3498_0_1.png":{"frame":{"x":99,"y":147,"w":12,"h":27},"rotated":false,"trimmed":false,"spriteSourceSize":{"x":0,"y":0,"w":12,"h":27},"sourceSize":{"w":12,"h":27},"pivot":{"x":0.5,"y":0.5}},"jacket_M_raincoat_h_wlk_rc_3498_0_2.png":{"frame":{"x":101,"y":201,"w":11,"h":27},"rotated":false,"trimmed":false,"spriteSourceSize":{"x":0,"y":0,"w":11,"h":27},"sourceSize":{"w":11,"h":27},"pivot":{"x":0.5,"y":0.5}},"jacket_M_raincoat_h_wlk_lc_3498_3_3.png":{"frame":{"x":106,"y":174,"w":10,"h":27},"rotated":false,"trimmed":false,"spriteSourceSize":{"x":0,"y":0,"w":10,"h":27},"sourceSize":{"w":10,"h":27},"pivot":{"x":0.5,"y":0.5}},"jacket_M_raincoat_h_wlk_rc_3498_3_1.png":{"frame":{"x":112,"y":147,"w":10,"h":27},"rotated":false,"trimmed":false,"spriteSourceSize":{"x":0,"y":0,"w":10,"h":27},"sourceSize":{"w":10,"h":27},"pivot":{"x":0.5,"y":0.5}},"jacket_M_raincoat_h_std_lc_3498_7_0.png":{"frame":{"x":122,"y":147,"w":9,"h":27},"rotated":false,"trimmed":false,"spriteSourceSize":{"x":0,"y":0,"w":9,"h":27},"sourceSize":{"w":9,"h":27},"pivot":{"x":0.5,"y":0.5}},"jacket_M_raincoat_h_wlk_lc_3498_7_0.png":{"frame":{"x":112,"y":201,"w":9,"h":27},"rotated":false,"trimmed":false,"spriteSourceSize":{"x":0,"y":0,"w":9,"h":27},"sourceSize":{"w":9,"h":27},"pivot":{"x":0.5,"y":0.5}},"jacket_M_raincoat_h_wlk_rc_3498_7_2.png":{"frame":{"x":116,"y":174,"w":9,"h":27},"rotated":false,"trimmed":false,"spriteSourceSize":{"x":0,"y":0,"w":9,"h":27},"sourceSize":{"w":9,"h":27},"pivot":{"x":0.5,"y":0.5}},"jacket_M_raincoat_h_std_rc_3498_7_0.png":{"frame":{"x":121,"y":201,"w":8,"h":27},"rotated":false,"trimmed":false,"spriteSourceSize":{"x":0,"y":0,"w":8,"h":27},"sourceSize":{"w":8,"h":27},"pivot":{"x":0.5,"y":0.5}},"jacket_M_raincoat_h_wlk_rc_3498_7_0.png":{"frame":{"x":125,"y":174,"w":8,"h":27},"rotated":false,"trimmed":false,"spriteSourceSize":{"x":0,"y":0,"w":8,"h":27},"sourceSize":{"w":8,"h":27},"pivot":{"x":0.5,"y":0.5}},"jacket_M_raincoat_h_wav_lc_3498_4_1.png":{"frame":{"x":133,"y":174,"w":24,"h":26},"rotated":false,"trimmed":false,"spriteSourceSize":{"x":0,"y":0,"w":24,"h":26},"sourceSize":{"w":24,"h":26},"pivot":{"x":0.5,"y":0.5}},"jacket_M_raincoat_h_crr_rc_3500_2_0.png":{"frame":{"x":131,"y":147,"w":17,"h":26},"rotated":false,"trimmed":false,"spriteSourceSize":{"x":0,"y":0,"w":17,"h":26},"sourceSize":{"w":17,"h":26},"pivot":{"x":0.5,"y":0.5}},"jacket_M_raincoat_h_wlk_rc_3498_0_0.png":{"frame":{"x":129,"y":201,"w":11,"h":26},"rotated":false,"trimmed":false,"spriteSourceSize":{"x":0,"y":0,"w":11,"h":26},"sourceSize":{"w":11,"h":26},"pivot":{"x":0.5,"y":0.5}},"jacket_M_raincoat_h_wlk_lc_3498_7_1.png":{"frame":{"x":132,"y":227,"w":9,"h":26},"rotated":false,"trimmed":false,"spriteSourceSize":{"x":0,"y":0,"w":9,"h":26},"sourceSize":{"w":9,"h":26},"pivot":{"x":0.5,"y":0.5}},"jacket_M_raincoat_h_wlk_lc_3498_7_3.png":{"frame":{"x":140,"y":200,"w":9,"h":26},"rotated":false,"trimmed":false,"spriteSourceSize":{"x":0,"y":0,"w":9,"h":26},"sourceSize":{"w":9,"h":26},"pivot":{"x":0.5,"y":0.5}},"jacket_M_raincoat_h_wlk_rc_3498_7_1.png":{"frame":{"x":141,"y":226,"w":9,"h":26},"rotated":false,"trimmed":false,"spriteSourceSize":{"x":0,"y":0,"w":9,"h":26},"sourceSize":{"w":9,"h":26},"pivot":{"x":0.5,"y":0.5}},"jacket_M_raincoat_h_wav_lc_3500_3_1.png":{"frame":{"x":143,"y":252,"w":15,"h":22},"rotated":false,"trimmed":false,"spriteSourceSize":{"x":0,"y":0,"w":15,"h":22},"sourceSize":{"w":15,"h":22},"pivot":{"x":0.5,"y":0.5}},"jacket_M_raincoat_h_wav_lc_3500_3_0.png":{"frame":{"x":158,"y":252,"w":13,"h":22},"rotated":false,"trimmed":false,"spriteSourceSize":{"x":0,"y":0,"w":13,"h":22},"sourceSize":{"w":13,"h":22},"pivot":{"x":0.5,"y":0.5}},"jacket_M_raincoat_h_crr_lc_3498_7_0.png":{"frame":{"x":171,"y":252,"w":9,"h":22},"rotated":false,"trimmed":false,"spriteSourceSize":{"x":0,"y":0,"w":9,"h":22},"sourceSize":{"w":9,"h":22},"pivot":{"x":0.5,"y":0.5}},"jacket_M_raincoat_h_wlk_rc_3498_7_3.png":{"frame":{"x":149,"y":200,"w":9,"h":26},"rotated":false,"trimmed":false,"spriteSourceSize":{"x":0,"y":0,"w":9,"h":26},"sourceSize":{"w":9,"h":26},"pivot":{"x":0.5,"y":0.5}},"jacket_M_raincoat_h_wlk_rc_3500_3_3.png":{"frame":{"x":150,"y":226,"w":7,"h":26},"rotated":false,"trimmed":false,"spriteSourceSize":{"x":0,"y":0,"w":7,"h":26},"sourceSize":{"w":7,"h":26},"pivot":{"x":0.5,"y":0.5}},"jacket_M_raincoat_h_wlk_rc_3498_0_3.png":{"frame":{"x":157,"y":226,"w":15,"h":25},"rotated":false,"trimmed":false,"spriteSourceSize":{"x":0,"y":0,"w":15,"h":25},"sourceSize":{"w":15,"h":25},"pivot":{"x":0.5,"y":0.5}},"jacket_M_raincoat_h_crr_lc_3498_2_0.png":{"frame":{"x":172,"y":226,"w":13,"h":25},"rotated":false,"trimmed":false,"spriteSourceSize":{"x":0,"y":0,"w":13,"h":25},"sourceSize":{"w":13,"h":25},"pivot":{"x":0.5,"y":0.5}},"jacket_M_raincoat_h_crr_rc_3498_4_0.png":{"frame":{"x":185,"y":226,"w":13,"h":25},"rotated":false,"trimmed":false,"spriteSourceSize":{"x":0,"y":0,"w":13,"h":25},"sourceSize":{"w":13,"h":25},"pivot":{"x":0.5,"y":0.5}},"jacket_M_raincoat_h_wlk_lc_3498_0_3.png":{"frame":{"x":72,"y":0,"w":11,"h":25},"rotated":false,"trimmed":false,"spriteSourceSize":{"x":0,"y":0,"w":11,"h":25},"sourceSize":{"w":11,"h":25},"pivot":{"x":0.5,"y":0.5}},"jacket_M_raincoat_h_wlk_lc_3498_0_1.png":{"frame":{"x":72,"y":25,"w":10,"h":25},"rotated":false,"trimmed":false,"spriteSourceSize":{"x":0,"y":0,"w":10,"h":25},"sourceSize":{"w":10,"h":25},"pivot":{"x":0.5,"y":0.5}},"jacket_M_raincoat_h_std_lc_3498_0_0.png":{"frame":{"x":72,"y":50,"w":9,"h":25},"rotated":false,"trimmed":false,"spriteSourceSize":{"x":0,"y":0,"w":9,"h":25},"sourceSize":{"w":9,"h":25},"pivot":{"x":0.5,"y":0.5}},"jacket_M_raincoat_h_wlk_lc_3498_0_0.png":{"frame":{"x":72,"y":75,"w":9,"h":25},"rotated":false,"trimmed":false,"spriteSourceSize":{"x":0,"y":0,"w":9,"h":25},"sourceSize":{"w":9,"h":25},"pivot":{"x":0.5,"y":0.5}},"jacket_M_raincoat_h_drk_rc_3498_0_0.png":{"frame":{"x":72,"y":100,"w":19,"h":20},"rotated":false,"trimmed":false,"spriteSourceSize":{"x":0,"y":0,"w":19,"h":20},"sourceSize":{"w":19,"h":20},"pivot":{"x":0.5,"y":0.5}},"jacket_M_raincoat_h_crr_lc_3498_1_0.png":{"frame":{"x":91,"y":100,"w":18,"h":20},"rotated":false,"trimmed":false,"spriteSourceSize":{"x":0,"y":0,"w":18,"h":20},"sourceSize":{"w":18,"h":20},"pivot":{"x":0.5,"y":0.5}},"jacket_M_raincoat_h_std_lc_3500_3_0.png":{"frame":{"x":81,"y":50,"w":8,"h":25},"rotated":false,"trimmed":false,"spriteSourceSize":{"x":0,"y":0,"w":8,"h":25},"sourceSize":{"w":8,"h":25},"pivot":{"x":0.5,"y":0.5}},"jacket_M_raincoat_h_std_rc_3500_3_0.png":{"frame":{"x":82,"y":25,"w":8,"h":25},"rotated":false,"trimmed":false,"spriteSourceSize":{"x":0,"y":0,"w":8,"h":25},"sourceSize":{"w":8,"h":25},"pivot":{"x":0.5,"y":0.5}},"jacket_M_raincoat_h_wlk_lc_3500_3_0.png":{"frame":{"x":89,"y":0,"w":8,"h":25},"rotated":false,"trimmed":false,"spriteSourceSize":{"x":0,"y":0,"w":8,"h":25},"sourceSize":{"w":8,"h":25},"pivot":{"x":0.5,"y":0.5}},"jacket_M_raincoat_h_crr_lc_3498_0_0.png":{"frame":{"x":83,"y":0,"w":6,"h":22},"rotated":false,"trimmed":false,"spriteSourceSize":{"x":0,"y":0,"w":6,"h":22},"sourceSize":{"w":6,"h":22},"pivot":{"x":0.5,"y":0.5}},"jacket_M_raincoat_h_wlk_rc_3500_3_0.png":{"frame":{"x":81,"y":75,"w":8,"h":25},"rotated":false,"trimmed":false,"spriteSourceSize":{"x":0,"y":0,"w":8,"h":25},"sourceSize":{"w":8,"h":25},"pivot":{"x":0.5,"y":0.5}},"jacket_M_raincoat_h_wlk_rc_3498_1_3.png":{"frame":{"x":89,"y":50,"w":17,"h":24},"rotated":false,"trimmed":false,"spriteSourceSize":{"x":0,"y":0,"w":17,"h":24},"sourceSize":{"w":17,"h":24},"pivot":{"x":0.5,"y":0.5}},"jacket_M_raincoat_h_wav_lc_3500_5_0.png":{"frame":{"x":90,"y":25,"w":14,"h":24},"rotated":false,"trimmed":false,"spriteSourceSize":{"x":0,"y":0,"w":14,"h":24},"sourceSize":{"w":14,"h":24},"pivot":{"x":0.5,"y":0.5}},"jacket_M_raincoat_h_wlk_lc_3498_2_1.png":{"frame":{"x":97,"y":0,"w":11,"h":24},"rotated":false,"trimmed":false,"spriteSourceSize":{"x":0,"y":0,"w":11,"h":24},"sourceSize":{"w":11,"h":24},"pivot":{"x":0.5,"y":0.5}},"jacket_M_raincoat_h_std_rc_3500_0_0.png":{"frame":{"x":104,"y":24,"w":10,"h":24},"rotated":false,"trimmed":false,"spriteSourceSize":{"x":0,"y":0,"w":10,"h":24},"sourceSize":{"w":10,"h":24},"pivot":{"x":0.5,"y":0.5}},"jacket_M_raincoat_h_lay_cc_3500_2_0.png":{"frame":{"x":108,"y":0,"w":53,"h":23},"rotated":false,"trimmed":false,"spriteSourceSize":{"x":0,"y":0,"w":53,"h":23},"sourceSize":{"w":53,"h":23},"pivot":{"x":0.5,"y":0.5}},"jacket_M_raincoat_h_crr_lc_3498_6_0.png":{"frame":{"x":89,"y":74,"w":19,"h":23},"rotated":false,"trimmed":false,"spriteSourceSize":{"x":0,"y":0,"w":19,"h":23},"sourceSize":{"w":19,"h":23},"pivot":{"x":0.5,"y":0.5}},"jacket_M_raincoat_h_wav_lc_3500_5_1.png":{"frame":{"x":106,"y":48,"w":13,"h":23},"rotated":false,"trimmed":false,"spriteSourceSize":{"x":0,"y":0,"w":13,"h":23},"sourceSize":{"w":13,"h":23},"pivot":{"x":0.5,"y":0.5}},"jacket_M_raincoat_h_wlk_lc_3498_1_1.png":{"frame":{"x":114,"y":23,"w":13,"h":23},"rotated":false,"trimmed":false,"spriteSourceSize":{"x":0,"y":0,"w":13,"h":23},"sourceSize":{"w":13,"h":23},"pivot":{"x":0.5,"y":0.5}},"jacket_M_raincoat_h_wlk_rc_3498_1_1.png":{"frame":{"x":108,"y":71,"w":13,"h":23},"rotated":false,"trimmed":false,"spriteSourceSize":{"x":0,"y":0,"w":13,"h":23},"sourceSize":{"w":13,"h":23},"pivot":{"x":0.5,"y":0.5}},"jacket_M_raincoat_h_std_lc_3498_1_0.png":{"frame":{"x":119,"y":46,"w":9,"h":23},"rotated":false,"trimmed":false,"spriteSourceSize":{"x":0,"y":0,"w":9,"h":23},"sourceSize":{"w":9,"h":23},"pivot":{"x":0.5,"y":0.5}},"jacket_M_raincoat_h_std_rc_3498_1_0.png":{"frame":{"x":127,"y":23,"w":9,"h":23},"rotated":false,"trimmed":false,"spriteSourceSize":{"x":0,"y":0,"w":9,"h":23},"sourceSize":{"w":9,"h":23},"pivot":{"x":0.5,"y":0.5}},"jacket_M_raincoat_h_std_lc_3498_2_0.png":{"frame":{"x":136,"y":23,"w":7,"h":23},"rotated":false,"trimmed":false,"spriteSourceSize":{"x":0,"y":0,"w":7,"h":23},"sourceSize":{"w":7,"h":23},"pivot":{"x":0.5,"y":0.5}},"jacket_M_raincoat_h_wlk_lc_3498_2_0.png":{"frame":{"x":109,"y":94,"w":7,"h":23},"rotated":false,"trimmed":false,"spriteSourceSize":{"x":0,"y":0,"w":7,"h":23},"sourceSize":{"w":7,"h":23},"pivot":{"x":0.5,"y":0.5}},"jacket_M_raincoat_h_wlk_lc_3498_2_2.png":{"frame":{"x":116,"y":94,"w":7,"h":23},"rotated":false,"trimmed":false,"spriteSourceSize":{"x":0,"y":0,"w":7,"h":23},"sourceSize":{"w":7,"h":23},"pivot":{"x":0.5,"y":0.5}},"jacket_M_raincoat_h_wlk_rc_3500_0_1.png":{"frame":{"x":121,"y":69,"w":7,"h":23},"rotated":false,"trimmed":false,"spriteSourceSize":{"x":0,"y":0,"w":7,"h":23},"sourceSize":{"w":7,"h":23},"pivot":{"x":0.5,"y":0.5}},"jacket_M_raincoat_h_crr_rc_3498_7_0.png":{"frame":{"x":123,"y":92,"w":9,"h":22},"rotated":false,"trimmed":false,"spriteSourceSize":{"x":0,"y":0,"w":9,"h":22},"sourceSize":{"w":9,"h":22},"pivot":{"x":0.5,"y":0.5}},"jacket_M_raincoat_h_wlk_rc_3500_0_0.png":{"frame":{"x":132,"y":92,"w":9,"h":22},"rotated":false,"trimmed":false,"spriteSourceSize":{"x":0,"y":0,"w":9,"h":22},"sourceSize":{"w":9,"h":22},"pivot":{"x":0.5,"y":0.5}},"jacket_M_raincoat_h_crr_lc_3500_3_0.png":{"frame":{"x":141,"y":92,"w":6,"h":22},"rotated":false,"trimmed":false,"spriteSourceSize":{"x":0,"y":0,"w":6,"h":22},"sourceSize":{"w":6,"h":22},"pivot":{"x":0.5,"y":0.5}},"jacket_M_raincoat_h_crr_rc_3498_6_0.png":{"frame":{"x":147,"y":92,"w":6,"h":22},"rotated":false,"trimmed":false,"spriteSourceSize":{"x":0,"y":0,"w":6,"h":22},"sourceSize":{"w":6,"h":22},"pivot":{"x":0.5,"y":0.5}},"jacket_M_raincoat_h_crr_rc_3500_3_0.png":{"frame":{"x":153,"y":92,"w":6,"h":22},"rotated":false,"trimmed":false,"spriteSourceSize":{"x":0,"y":0,"w":6,"h":22},"sourceSize":{"w":6,"h":22},"pivot":{"x":0.5,"y":0.5}},"jacket_M_raincoat_h_wlk_lc_3500_7_0.png":{"frame":{"x":159,"y":92,"w":6,"h":22},"rotated":false,"trimmed":false,"spriteSourceSize":{"x":0,"y":0,"w":6,"h":22},"sourceSize":{"w":6,"h":22},"pivot":{"x":0.5,"y":0.5}},"jacket_M_raincoat_h_wlk_lc_3500_7_2.png":{"frame":{"x":165,"y":92,"w":6,"h":22},"rotated":false,"trimmed":false,"spriteSourceSize":{"x":0,"y":0,"w":6,"h":22},"sourceSize":{"w":6,"h":22},"pivot":{"x":0.5,"y":0.5}},"jacket_M_raincoat_h_wlk_rc_3500_7_0.png":{"frame":{"x":139,"y":114,"w":6,"h":22},"rotated":false,"trimmed":false,"spriteSourceSize":{"x":0,"y":0,"w":6,"h":22},"sourceSize":{"w":6,"h":22},"pivot":{"x":0.5,"y":0.5}},"jacket_M_raincoat_h_lay_rc_3500_2_0.png":{"frame":{"x":139,"y":136,"w":19,"h":11},"rotated":false,"trimmed":false,"spriteSourceSize":{"x":0,"y":0,"w":19,"h":11},"sourceSize":{"w":19,"h":11},"pivot":{"x":0.5,"y":0.5}},"jacket_M_raincoat_h_wlk_rc_3500_7_2.png":{"frame":{"x":145,"y":114,"w":6,"h":22},"rotated":false,"trimmed":false,"spriteSourceSize":{"x":0,"y":0,"w":6,"h":22},"sourceSize":{"w":6,"h":22},"pivot":{"x":0.5,"y":0.5}},"jacket_M_raincoat_h_wav_lc_3500_6_1.png":{"frame":{"x":151,"y":114,"w":22,"h":21},"rotated":false,"trimmed":false,"spriteSourceSize":{"x":0,"y":0,"w":22,"h":21},"sourceSize":{"w":22,"h":21},"pivot":{"x":0.5,"y":0.5}},"jacket_M_raincoat_h_wav_lc_3500_2_0.png":{"frame":{"x":148,"y":147,"w":12,"h":21},"rotated":false,"trimmed":false,"spriteSourceSize":{"x":0,"y":0,"w":12,"h":21},"sourceSize":{"w":12,"h":21},"pivot":{"x":0.5,"y":0.5}},"jacket_M_raincoat_h_lay_lc_3500_2_0.png":{"frame":{"x":158,"y":135,"w":19,"h":10},"rotated":false,"trimmed":false,"spriteSourceSize":{"x":0,"y":0,"w":19,"h":10},"sourceSize":{"w":19,"h":10},"pivot":{"x":0.5,"y":0.5}},"jacket_M_raincoat_h_wlk_rc_3500_0_3.png":{"frame":{"x":157,"y":168,"w":12,"h":21},"rotated":false,"trimmed":false,"spriteSourceSize":{"x":0,"y":0,"w":12,"h":21},"sourceSize":{"w":12,"h":21},"pivot":{"x":0.5,"y":0.5}},"jacket_M_raincoat_h_wlk_lc_3500_7_3.png":{"frame":{"x":160,"y":145,"w":6,"h":21},"rotated":false,"trimmed":false,"spriteSourceSize":{"x":0,"y":0,"w":6,"h":21},"sourceSize":{"w":6,"h":21},"pivot":{"x":0.5,"y":0.5}},"jacket_M_raincoat_h_wlk_rc_3500_7_1.png":{"frame":{"x":166,"y":145,"w":6,"h":21},"rotated":false,"trimmed":false,"spriteSourceSize":{"x":0,"y":0,"w":6,"h":21},"sourceSize":{"w":6,"h":21},"pivot":{"x":0.5,"y":0.5}},"jacket_M_raincoat_h_std_lc_3500_7_0.png":{"frame":{"x":158,"y":189,"w":5,"h":21},"rotated":false,"trimmed":false,"spriteSourceSize":{"x":0,"y":0,"w":5,"h":21},"sourceSize":{"w":5,"h":21},"pivot":{"x":0.5,"y":0.5}},"jacket_M_raincoat_h_drk_rc_3500_3_0.png":{"frame":{"x":158,"y":210,"w":14,"h":16},"rotated":false,"trimmed":false,"spriteSourceSize":{"x":0,"y":0,"w":14,"h":16},"sourceSize":{"w":14,"h":16},"pivot":{"x":0.5,"y":0.5}},"jacket_M_raincoat_h_crr_lc_3500_2_0.png":{"frame":{"x":172,"y":210,"w":8,"h":16},"rotated":false,"trimmed":false,"spriteSourceSize":{"x":0,"y":0,"w":8,"h":16},"sourceSize":{"w":8,"h":16},"pivot":{"x":0.5,"y":0.5}},"jacket_M_raincoat_h_crr_rc_3500_4_0.png":{"frame":{"x":180,"y":210,"w":8,"h":16},"rotated":false,"trimmed":false,"spriteSourceSize":{"x":0,"y":0,"w":8,"h":16},"sourceSize":{"w":8,"h":16},"pivot":{"x":0.5,"y":0.5}},"jacket_M_raincoat_h_wlk_lc_3498_2_3.png":{"frame":{"x":163,"y":189,"w":5,"h":21},"rotated":false,"trimmed":false,"spriteSourceSize":{"x":0,"y":0,"w":5,"h":21},"sourceSize":{"w":5,"h":21},"pivot":{"x":0.5,"y":0.5}},"jacket_M_raincoat_h_std_rc_3500_7_0.png":{"frame":{"x":168,"y":189,"w":4,"h":21},"rotated":false,"trimmed":false,"spriteSourceSize":{"x":0,"y":0,"w":4,"h":21},"sourceSize":{"w":4,"h":21},"pivot":{"x":0.5,"y":0.5}},"jacket_M_raincoat_h_crr_lc_3498_5_0.png":{"frame":{"x":172,"y":189,"w":18,"h":20},"rotated":false,"trimmed":false,"spriteSourceSize":{"x":0,"y":0,"w":18,"h":20},"sourceSize":{"w":18,"h":20},"pivot":{"x":0.5,"y":0.5}},"jacket_M_raincoat_h_crr_lc_3500_6_0.png":{"frame":{"x":188,"y":209,"w":17,"h":17},"rotated":false,"trimmed":false,"spriteSourceSize":{"x":0,"y":0,"w":17,"h":17},"sourceSize":{"w":17,"h":17},"pivot":{"x":0.5,"y":0.5}},"jacket_M_raincoat_h_crr_rc_3500_0_0.png":{"frame":{"x":205,"y":209,"w":17,"h":17},"rotated":false,"trimmed":false,"spriteSourceSize":{"x":0,"y":0,"w":17,"h":17},"sourceSize":{"w":17,"h":17},"pivot":{"x":0.5,"y":0.5}},"jacket_M_raincoat_h_lay_rc_3498_2_0.png":{"frame":{"x":169,"y":166,"w":28,"h":19},"rotated":false,"trimmed":false,"spriteSourceSize":{"x":0,"y":0,"w":28,"h":19},"sourceSize":{"w":28,"h":19},"pivot":{"x":0.5,"y":0.5}},"jacket_M_raincoat_h_wav_lc_3500_4_0.png":{"frame":{"x":172,"y":145,"w":22,"h":19},"rotated":false,"trimmed":false,"spriteSourceSize":{"x":0,"y":0,"w":22,"h":19},"sourceSize":{"w":22,"h":19},"pivot":{"x":0.5,"y":0.5}},"jacket_M_raincoat_h_wav_lc_3500_7_1.png":{"frame":{"x":190,"y":185,"w":12,"h":19},"rotated":false,"trimmed":false,"spriteSourceSize":{"x":0,"y":0,"w":12,"h":19},"sourceSize":{"w":12,"h":19},"pivot":{"x":0.5,"y":0.5}},"jacket_M_raincoat_h_wav_lc_3500_1_1.png":{"frame":{"x":128,"y":46,"w":11,"h":19},"rotated":false,"trimmed":false,"spriteSourceSize":{"x":0,"y":0,"w":11,"h":19},"sourceSize":{"w":11,"h":19},"pivot":{"x":0.5,"y":0.5}},"jacket_M_raincoat_h_wav_lc_3500_1_0.png":{"frame":{"x":128,"y":65,"w":10,"h":19},"rotated":false,"trimmed":false,"spriteSourceSize":{"x":0,"y":0,"w":10,"h":19},"sourceSize":{"w":10,"h":19},"pivot":{"x":0.5,"y":0.5}},"jacket_M_raincoat_h_wav_lc_3500_7_0.png":{"frame":{"x":138,"y":65,"w":10,"h":19},"rotated":false,"trimmed":false,"spriteSourceSize":{"x":0,"y":0,"w":10,"h":19},"sourceSize":{"w":10,"h":19},"pivot":{"x":0.5,"y":0.5}},"jacket_M_raincoat_h_wlk_rc_3500_1_3.png":{"frame":{"x":139,"y":46,"w":10,"h":19},"rotated":false,"trimmed":false,"spriteSourceSize":{"x":0,"y":0,"w":10,"h":19},"sourceSize":{"w":10,"h":19},"pivot":{"x":0.5,"y":0.5}},"jacket_M_raincoat_h_wav_lc_3500_0_0.png":{"frame":{"x":148,"y":23,"w":8,"h":19},"rotated":false,"trimmed":false,"spriteSourceSize":{"x":0,"y":0,"w":8,"h":19},"sourceSize":{"w":8,"h":19},"pivot":{"x":0.5,"y":0.5}},"jacket_M_raincoat_h_std_cc_3499_1_0.png":{"frame":{"x":143,"y":23,"w":4,"h":13},"rotated":false,"trimmed":false,"spriteSourceSize":{"x":0,"y":0,"w":4,"h":13},"sourceSize":{"w":4,"h":13},"pivot":{"x":0.5,"y":0.5}},"jacket_M_raincoat_h_drk_rc_3500_2_0.png":{"frame":{"x":148,"y":65,"w":29,"h":18},"rotated":false,"trimmed":false,"spriteSourceSize":{"x":0,"y":0,"w":29,"h":18},"sourceSize":{"w":29,"h":18},"pivot":{"x":0.5,"y":0.5}},"jacket_M_raincoat_h_lay_lc_3498_2_0.png":{"frame":{"x":149,"y":42,"w":24,"h":18},"rotated":false,"trimmed":false,"spriteSourceSize":{"x":0,"y":0,"w":24,"h":18},"sourceSize":{"w":24,"h":18},"pivot":{"x":0.5,"y":0.5}},"jacket_M_raincoat_h_wav_lc_3500_4_1.png":{"frame":{"x":156,"y":23,"w":20,"h":18},"rotated":false,"trimmed":false,"spriteSourceSize":{"x":0,"y":0,"w":20,"h":18},"sourceSize":{"w":20,"h":18},"pivot":{"x":0.5,"y":0.5}},"jacket_M_raincoat_h_drk_rc_3498_4_0.png":{"frame":{"x":161,"y":0,"w":14,"h":18},"rotated":false,"trimmed":false,"spriteSourceSize":{"x":0,"y":0,"w":14,"h":18},"sourceSize":{"w":14,"h":18},"pivot":{"x":0.5,"y":0.5}},"jacket_M_raincoat_h_wav_lc_3500_0_1.png":{"frame":{"x":175,"y":0,"w":11,"h":18},"rotated":false,"trimmed":false,"spriteSourceSize":{"x":0,"y":0,"w":11,"h":18},"sourceSize":{"w":11,"h":18},"pivot":{"x":0.5,"y":0.5}},"jacket_M_raincoat_h_wlk_lc_3500_2_1.png":{"frame":{"x":173,"y":41,"w":7,"h":18},"rotated":false,"trimmed":false,"spriteSourceSize":{"x":0,"y":0,"w":7,"h":18},"sourceSize":{"w":7,"h":18},"pivot":{"x":0.5,"y":0.5}},"jacket_M_raincoat_h_std_lc_3500_1_0.png":{"frame":{"x":177,"y":18,"w":6,"h":18},"rotated":false,"trimmed":false,"spriteSourceSize":{"x":0,"y":0,"w":6,"h":18},"sourceSize":{"w":6,"h":18},"pivot":{"x":0.5,"y":0.5}},"jacket_M_raincoat_h_std_rc_3500_1_0.png":{"frame":{"x":171,"y":83,"w":6,"h":18},"rotated":false,"trimmed":false,"spriteSourceSize":{"x":0,"y":0,"w":6,"h":18},"sourceSize":{"w":6,"h":18},"pivot":{"x":0.5,"y":0.5}},"jacket_M_raincoat_h_drk_rc_3500_0_0.png":{"frame":{"x":171,"y":101,"w":16,"h":13},"rotated":false,"trimmed":false,"spriteSourceSize":{"x":0,"y":0,"w":16,"h":13},"sourceSize":{"w":16,"h":13},"pivot":{"x":0.5,"y":0.5}},"jacket_M_raincoat_h_wlk_lc_3500_1_0.png":{"frame":{"x":173,"y":114,"w":6,"h":18},"rotated":false,"trimmed":false,"spriteSourceSize":{"x":0,"y":0,"w":6,"h":18},"sourceSize":{"w":6,"h":18},"pivot":{"x":0.5,"y":0.5}},"jacket_M_raincoat_h_drk_rc_3500_4_0.png":{"frame":{"x":177,"y":132,"w":12,"h":13},"rotated":false,"trimmed":false,"spriteSourceSize":{"x":0,"y":0,"w":12,"h":13},"sourceSize":{"w":12,"h":13},"pivot":{"x":0.5,"y":0.5}},"jacket_M_raincoat_h_wlk_lc_3500_1_1.png":{"frame":{"x":179,"y":114,"w":6,"h":18},"rotated":false,"trimmed":false,"spriteSourceSize":{"x":0,"y":0,"w":6,"h":18},"sourceSize":{"w":6,"h":18},"pivot":{"x":0.5,"y":0.5}},"jacket_M_raincoat_h_crr_lc_3500_1_0.png":{"frame":{"x":185,"y":114,"w":14,"h":17},"rotated":false,"trimmed":false,"spriteSourceSize":{"x":0,"y":0,"w":14,"h":17},"sourceSize":{"w":14,"h":17},"pivot":{"x":0.5,"y":0.5}},"jacket_M_raincoat_h_wav_lc_3500_2_1.png":{"frame":{"x":189,"y":131,"w":12,"h":14},"rotated":false,"trimmed":false,"spriteSourceSize":{"x":0,"y":0,"w":12,"h":14},"sourceSize":{"w":12,"h":14},"pivot":{"x":0.5,"y":0.5}},"jacket_M_raincoat_h_crr_rc_3500_5_0.png":{"frame":{"x":194,"y":145,"w":14,"h":17},"rotated":false,"trimmed":false,"spriteSourceSize":{"x":0,"y":0,"w":14,"h":17},"sourceSize":{"w":14,"h":17},"pivot":{"x":0.5,"y":0.5}},"jacket_M_raincoat_h_drk_rc_3498_7_0.png":{"frame":{"x":197,"y":162,"w":10,"h":17},"rotated":false,"trimmed":false,"spriteSourceSize":{"x":0,"y":0,"w":10,"h":17},"sourceSize":{"w":10,"h":17},"pivot":{"x":0.5,"y":0.5}},"jacket_M_raincoat_h_wlk_lc_3500_2_0.png":{"frame":{"x":202,"y":179,"w":3,"h":17},"rotated":false,"trimmed":false,"spriteSourceSize":{"x":0,"y":0,"w":3,"h":17},"sourceSize":{"w":3,"h":17},"pivot":{"x":0.5,"y":0.5}},"jacket_M_raincoat_h_wlk_lc_3500_3_3.png":{"frame":{"x":202,"y":196,"w":6,"h":13},"rotated":false,"trimmed":false,"spriteSourceSize":{"x":0,"y":0,"w":6,"h":13},"sourceSize":{"w":6,"h":13},"pivot":{"x":0.5,"y":0.5}},"jacket_M_raincoat_h_wlk_rc_3500_3_1.png":{"frame":{"x":208,"y":196,"w":6,"h":13},"rotated":false,"trimmed":false,"spriteSourceSize":{"x":0,"y":0,"w":6,"h":13},"sourceSize":{"w":6,"h":13},"pivot":{"x":0.5,"y":0.5}},"jacket_M_raincoat_h_wlk_lc_3500_2_2.png":{"frame":{"x":205,"y":179,"w":3,"h":17},"rotated":false,"trimmed":false,"spriteSourceSize":{"x":0,"y":0,"w":3,"h":17},"sourceSize":{"w":3,"h":17},"pivot":{"x":0.5,"y":0.5}},"jacket_M_raincoat_h_std_lc_3500_2_0.png":{"frame":{"x":208,"y":179,"w":3,"h":16},"rotated":false,"trimmed":false,"spriteSourceSize":{"x":0,"y":0,"w":3,"h":16},"sourceSize":{"w":3,"h":16},"pivot":{"x":0.5,"y":0.5}},"jacket_M_raincoat_h_crr_lc_3500_5_0.png":{"frame":{"x":211,"y":179,"w":14,"h":15},"rotated":false,"trimmed":false,"spriteSourceSize":{"x":0,"y":0,"w":14,"h":15},"sourceSize":{"w":14,"h":15},"pivot":{"x":0.5,"y":0.5}},"jacket_M_raincoat_h_crr_rc_3500_1_0.png":{"frame":{"x":214,"y":194,"w":14,"h":15},"rotated":false,"trimmed":false,"spriteSourceSize":{"x":0,"y":0,"w":14,"h":15},"sourceSize":{"w":14,"h":15},"pivot":{"x":0.5,"y":0.5}},"jacket_M_raincoat_h_crr_lc_3500_4_0.png":{"frame":{"x":207,"y":162,"w":12,"h":15},"rotated":false,"trimmed":false,"spriteSourceSize":{"x":0,"y":0,"w":12,"h":15},"sourceSize":{"w":12,"h":15},"pivot":{"x":0.5,"y":0.5}},"jacket_M_raincoat_h_wlk_lc_3498_1_3.png":{"frame":{"x":177,"y":59,"w":3,"h":14},"rotated":false,"trimmed":false,"spriteSourceSize":{"x":0,"y":0,"w":3,"h":14},"sourceSize":{"w":3,"h":14},"pivot":{"x":0.5,"y":0.5}},"jacket_M_raincoat_h_crr_lc_3500_7_0.png":{"frame":{"x":177,"y":73,"w":2,"h":13},"rotated":false,"trimmed":false,"spriteSourceSize":{"x":0,"y":0,"w":2,"h":13},"sourceSize":{"w":2,"h":13},"pivot":{"x":0.5,"y":0.5}},"jacket_M_raincoat_h_crr_rc_3500_7_0.png":{"frame":{"x":177,"y":86,"w":2,"h":13},"rotated":false,"trimmed":false,"spriteSourceSize":{"x":0,"y":0,"w":2,"h":13},"sourceSize":{"w":2,"h":13},"pivot":{"x":0.5,"y":0.5}},"jacket_M_raincoat_h_crr_rc_3498_1_0.png":{"frame":{"x":91,"y":100,"w":18,"h":20},"rotated":false,"trimmed":false,"spriteSourceSize":{"x":0,"y":0,"w":18,"h":20},"sourceSize":{"w":18,"h":20},"pivot":{"x":0.5,"y":0.5}},"jacket_M_raincoat_h_crr_rc_3498_5_0.png":{"frame":{"x":172,"y":189,"w":18,"h":20},"rotated":false,"trimmed":false,"spriteSourceSize":{"x":0,"y":0,"w":18,"h":20},"sourceSize":{"w":18,"h":20},"pivot":{"x":0.5,"y":0.5}},"jacket_M_raincoat_h_crr_lc_3499_1_0.png":{"frame":{"x":38,"y":353,"w":1,"h":1},"rotated":false,"trimmed":false,"spriteSourceSize":{"x":0,"y":0,"w":1,"h":1},"sourceSize":{"w":1,"h":1},"pivot":{"x":0.5,"y":0.5}},"jacket_M_raincoat_h_crr_lc_3499_2_0.png":{"frame":{"x":38,"y":353,"w":1,"h":1},"rotated":false,"trimmed":false,"spriteSourceSize":{"x":0,"y":0,"w":1,"h":1},"sourceSize":{"w":1,"h":1},"pivot":{"x":0.5,"y":0.5}},"jacket_M_raincoat_h_crr_lc_3499_3_0.png":{"frame":{"x":38,"y":353,"w":1,"h":1},"rotated":false,"trimmed":false,"spriteSourceSize":{"x":0,"y":0,"w":1,"h":1},"sourceSize":{"w":1,"h":1},"pivot":{"x":0.5,"y":0.5}},"jacket_M_raincoat_h_crr_lc_3499_4_0.png":{"frame":{"x":38,"y":353,"w":1,"h":1},"rotated":false,"trimmed":false,"spriteSourceSize":{"x":0,"y":0,"w":1,"h":1},"sourceSize":{"w":1,"h":1},"pivot":{"x":0.5,"y":0.5}},"jacket_M_raincoat_h_crr_lc_3499_5_0.png":{"frame":{"x":38,"y":353,"w":1,"h":1},"rotated":false,"trimmed":false,"spriteSourceSize":{"x":0,"y":0,"w":1,"h":1},"sourceSize":{"w":1,"h":1},"pivot":{"x":0.5,"y":0.5}},"jacket_M_raincoat_h_crr_lc_3499_6_0.png":{"frame":{"x":38,"y":353,"w":1,"h":1},"rotated":false,"trimmed":false,"spriteSourceSize":{"x":0,"y":0,"w":1,"h":1},"sourceSize":{"w":1,"h":1},"pivot":{"x":0.5,"y":0.5}},"jacket_M_raincoat_h_crr_lc_3499_7_0.png":{"frame":{"x":38,"y":353,"w":1,"h":1},"rotated":false,"trimmed":false,"spriteSourceSize":{"x":0,"y":0,"w":1,"h":1},"sourceSize":{"w":1,"h":1},"pivot":{"x":0.5,"y":0.5}},"jacket_M_raincoat_h_crr_rc_3499_0_0.png":{"frame":{"x":38,"y":353,"w":1,"h":1},"rotated":false,"trimmed":false,"spriteSourceSize":{"x":0,"y":0,"w":1,"h":1},"sourceSize":{"w":1,"h":1},"pivot":{"x":0.5,"y":0.5}},"jacket_M_raincoat_h_crr_rc_3499_1_0.png":{"frame":{"x":38,"y":353,"w":1,"h":1},"rotated":false,"trimmed":false,"spriteSourceSize":{"x":0,"y":0,"w":1,"h":1},"sourceSize":{"w":1,"h":1},"pivot":{"x":0.5,"y":0.5}},"jacket_M_raincoat_h_crr_rc_3499_2_0.png":{"frame":{"x":38,"y":353,"w":1,"h":1},"rotated":false,"trimmed":false,"spriteSourceSize":{"x":0,"y":0,"w":1,"h":1},"sourceSize":{"w":1,"h":1},"pivot":{"x":0.5,"y":0.5}},"jacket_M_raincoat_h_crr_rc_3499_3_0.png":{"frame":{"x":38,"y":353,"w":1,"h":1},"rotated":false,"trimmed":false,"spriteSourceSize":{"x":0,"y":0,"w":1,"h":1},"sourceSize":{"w":1,"h":1},"pivot":{"x":0.5,"y":0.5}},"jacket_M_raincoat_h_crr_rc_3499_4_0.png":{"frame":{"x":38,"y":353,"w":1,"h":1},"rotated":false,"trimmed":false,"spriteSourceSize":{"x":0,"y":0,"w":1,"h":1},"sourceSize":{"w":1,"h":1},"pivot":{"x":0.5,"y":0.5}},"jacket_M_raincoat_h_crr_rc_3499_5_0.png":{"frame":{"x":38,"y":353,"w":1,"h":1},"rotated":false,"trimmed":false,"spriteSourceSize":{"x":0,"y":0,"w":1,"h":1},"sourceSize":{"w":1,"h":1},"pivot":{"x":0.5,"y":0.5}},"jacket_M_raincoat_h_crr_rc_3499_6_0.png":{"frame":{"x":38,"y":353,"w":1,"h":1},"rotated":false,"trimmed":false,"spriteSourceSize":{"x":0,"y":0,"w":1,"h":1},"sourceSize":{"w":1,"h":1},"pivot":{"x":0.5,"y":0.5}},"jacket_M_raincoat_h_crr_rc_3499_7_0.png":{"frame":{"x":38,"y":353,"w":1,"h":1},"rotated":false,"trimmed":false,"spriteSourceSize":{"x":0,"y":0,"w":1,"h":1},"sourceSize":{"w":1,"h":1},"pivot":{"x":0.5,"y":0.5}},"jacket_M_raincoat_h_drk_rc_3499_0_0.png":{"frame":{"x":38,"y":353,"w":1,"h":1},"rotated":false,"trimmed":false,"spriteSourceSize":{"x":0,"y":0,"w":1,"h":1},"sourceSize":{"w":1,"h":1},"pivot":{"x":0.5,"y":0.5}},"jacket_M_raincoat_h_drk_rc_3499_1_0.png":{"frame":{"x":38,"y":353,"w":1,"h":1},"rotated":false,"trimmed":false,"spriteSourceSize":{"x":0,"y":0,"w":1,"h":1},"sourceSize":{"w":1,"h":1},"pivot":{"x":0.5,"y":0.5}},"jacket_M_raincoat_h_drk_rc_3499_2_0.png":{"frame":{"x":38,"y":353,"w":1,"h":1},"rotated":false,"trimmed":false,"spriteSourceSize":{"x":0,"y":0,"w":1,"h":1},"sourceSize":{"w":1,"h":1},"pivot":{"x":0.5,"y":0.5}},"jacket_M_raincoat_h_drk_rc_3499_3_0.png":{"frame":{"x":38,"y":353,"w":1,"h":1},"rotated":false,"trimmed":false,"spriteSourceSize":{"x":0,"y":0,"w":1,"h":1},"sourceSize":{"w":1,"h":1},"pivot":{"x":0.5,"y":0.5}},"jacket_M_raincoat_h_drk_rc_3499_4_0.png":{"frame":{"x":38,"y":353,"w":1,"h":1},"rotated":false,"trimmed":false,"spriteSourceSize":{"x":0,"y":0,"w":1,"h":1},"sourceSize":{"w":1,"h":1},"pivot":{"x":0.5,"y":0.5}},"jacket_M_raincoat_h_drk_rc_3499_5_0.png":{"frame":{"x":38,"y":353,"w":1,"h":1},"rotated":false,"trimmed":false,"spriteSourceSize":{"x":0,"y":0,"w":1,"h":1},"sourceSize":{"w":1,"h":1},"pivot":{"x":0.5,"y":0.5}},"jacket_M_raincoat_h_drk_rc_3499_6_0.png":{"frame":{"x":38,"y":353,"w":1,"h":1},"rotated":false,"trimmed":false,"spriteSourceSize":{"x":0,"y":0,"w":1,"h":1},"sourceSize":{"w":1,"h":1},"pivot":{"x":0.5,"y":0.5}},"jacket_M_raincoat_h_drk_rc_3499_7_0.png":{"frame":{"x":38,"y":353,"w":1,"h":1},"rotated":false,"trimmed":false,"spriteSourceSize":{"x":0,"y":0,"w":1,"h":1},"sourceSize":{"w":1,"h":1},"pivot":{"x":0.5,"y":0.5}},"jacket_M_raincoat_h_lay_lc_3499_2_0.png":{"frame":{"x":38,"y":353,"w":1,"h":1},"rotated":false,"trimmed":false,"spriteSourceSize":{"x":0,"y":0,"w":1,"h":1},"sourceSize":{"w":1,"h":1},"pivot":{"x":0.5,"y":0.5}},"jacket_M_raincoat_h_lay_rc_3499_2_0.png":{"frame":{"x":38,"y":353,"w":1,"h":1},"rotated":false,"trimmed":false,"spriteSourceSize":{"x":0,"y":0,"w":1,"h":1},"sourceSize":{"w":1,"h":1},"pivot":{"x":0.5,"y":0.5}},"jacket_M_raincoat_h_std_cc_3499_7_0.png":{"frame":{"x":38,"y":353,"w":1,"h":1},"rotated":false,"trimmed":false,"spriteSourceSize":{"x":0,"y":0,"w":1,"h":1},"sourceSize":{"w":1,"h":1},"pivot":{"x":0.5,"y":0.5}},"jacket_M_raincoat_h_std_lc_3499_0_0.png":{"frame":{"x":38,"y":353,"w":1,"h":1},"rotated":false,"trimmed":false,"spriteSourceSize":{"x":0,"y":0,"w":1,"h":1},"sourceSize":{"w":1,"h":1},"pivot":{"x":0.5,"y":0.5}},"jacket_M_raincoat_h_std_lc_3499_1_0.png":{"frame":{"x":38,"y":353,"w":1,"h":1},"rotated":false,"trimmed":false,"spriteSourceSize":{"x":0,"y":0,"w":1,"h":1},"sourceSize":{"w":1,"h":1},"pivot":{"x":0.5,"y":0.5}},"jacket_M_raincoat_h_std_lc_3499_2_0.png":{"frame":{"x":38,"y":353,"w":1,"h":1},"rotated":false,"trimmed":false,"spriteSourceSize":{"x":0,"y":0,"w":1,"h":1},"sourceSize":{"w":1,"h":1},"pivot":{"x":0.5,"y":0.5}},"jacket_M_raincoat_h_std_lc_3499_3_0.png":{"frame":{"x":38,"y":353,"w":1,"h":1},"rotated":false,"trimmed":false,"spriteSourceSize":{"x":0,"y":0,"w":1,"h":1},"sourceSize":{"w":1,"h":1},"pivot":{"x":0.5,"y":0.5}},"jacket_M_raincoat_h_std_lc_3499_7_0.png":{"frame":{"x":38,"y":353,"w":1,"h":1},"rotated":false,"trimmed":false,"spriteSourceSize":{"x":0,"y":0,"w":1,"h":1},"sourceSize":{"w":1,"h":1},"pivot":{"x":0.5,"y":0.5}},"jacket_M_raincoat_h_std_rc_3499_1_0.png":{"frame":{"x":38,"y":353,"w":1,"h":1},"rotated":false,"trimmed":false,"spriteSourceSize":{"x":0,"y":0,"w":1,"h":1},"sourceSize":{"w":1,"h":1},"pivot":{"x":0.5,"y":0.5}},"jacket_M_raincoat_h_std_rc_3499_2_0.png":{"frame":{"x":38,"y":353,"w":1,"h":1},"rotated":false,"trimmed":false,"spriteSourceSize":{"x":0,"y":0,"w":1,"h":1},"sourceSize":{"w":1,"h":1},"pivot":{"x":0.5,"y":0.5}},"jacket_M_raincoat_h_std_rc_3499_3_0.png":{"frame":{"x":38,"y":353,"w":1,"h":1},"rotated":false,"trimmed":false,"spriteSourceSize":{"x":0,"y":0,"w":1,"h":1},"sourceSize":{"w":1,"h":1},"pivot":{"x":0.5,"y":0.5}},"jacket_M_raincoat_h_std_rc_3499_7_0.png":{"frame":{"x":38,"y":353,"w":1,"h":1},"rotated":false,"trimmed":false,"spriteSourceSize":{"x":0,"y":0,"w":1,"h":1},"sourceSize":{"w":1,"h":1},"pivot":{"x":0.5,"y":0.5}},"jacket_M_raincoat_h_wav_lc_3499_0_0.png":{"frame":{"x":38,"y":353,"w":1,"h":1},"rotated":false,"trimmed":false,"spriteSourceSize":{"x":0,"y":0,"w":1,"h":1},"sourceSize":{"w":1,"h":1},"pivot":{"x":0.5,"y":0.5}},"jacket_M_raincoat_h_wav_lc_3499_0_1.png":{"frame":{"x":38,"y":353,"w":1,"h":1},"rotated":false,"trimmed":false,"spriteSourceSize":{"x":0,"y":0,"w":1,"h":1},"sourceSize":{"w":1,"h":1},"pivot":{"x":0.5,"y":0.5}},"jacket_M_raincoat_h_wav_lc_3499_1_0.png":{"frame":{"x":38,"y":353,"w":1,"h":1},"rotated":false,"trimmed":false,"spriteSourceSize":{"x":0,"y":0,"w":1,"h":1},"sourceSize":{"w":1,"h":1},"pivot":{"x":0.5,"y":0.5}},"jacket_M_raincoat_h_wav_lc_3499_1_1.png":{"frame":{"x":38,"y":353,"w":1,"h":1},"rotated":false,"trimmed":false,"spriteSourceSize":{"x":0,"y":0,"w":1,"h":1},"sourceSize":{"w":1,"h":1},"pivot":{"x":0.5,"y":0.5}},"jacket_M_raincoat_h_wav_lc_3499_2_1.png":{"frame":{"x":38,"y":353,"w":1,"h":1},"rotated":false,"trimmed":false,"spriteSourceSize":{"x":0,"y":0,"w":1,"h":1},"sourceSize":{"w":1,"h":1},"pivot":{"x":0.5,"y":0.5}},"jacket_M_raincoat_h_wav_lc_3499_3_0.png":{"frame":{"x":38,"y":353,"w":1,"h":1},"rotated":false,"trimmed":false,"spriteSourceSize":{"x":0,"y":0,"w":1,"h":1},"sourceSize":{"w":1,"h":1},"pivot":{"x":0.5,"y":0.5}},"jacket_M_raincoat_h_wav_lc_3499_3_1.png":{"frame":{"x":38,"y":353,"w":1,"h":1},"rotated":false,"trimmed":false,"spriteSourceSize":{"x":0,"y":0,"w":1,"h":1},"sourceSize":{"w":1,"h":1},"pivot":{"x":0.5,"y":0.5}},"jacket_M_raincoat_h_wav_lc_3499_4_0.png":{"frame":{"x":38,"y":353,"w":1,"h":1},"rotated":false,"trimmed":false,"spriteSourceSize":{"x":0,"y":0,"w":1,"h":1},"sourceSize":{"w":1,"h":1},"pivot":{"x":0.5,"y":0.5}},"jacket_M_raincoat_h_wav_lc_3499_4_1.png":{"frame":{"x":38,"y":353,"w":1,"h":1},"rotated":false,"trimmed":false,"spriteSourceSize":{"x":0,"y":0,"w":1,"h":1},"sourceSize":{"w":1,"h":1},"pivot":{"x":0.5,"y":0.5}},"jacket_M_raincoat_h_wav_lc_3499_5_0.png":{"frame":{"x":38,"y":353,"w":1,"h":1},"rotated":false,"trimmed":false,"spriteSourceSize":{"x":0,"y":0,"w":1,"h":1},"sourceSize":{"w":1,"h":1},"pivot":{"x":0.5,"y":0.5}},"jacket_M_raincoat_h_wav_lc_3499_5_1.png":{"frame":{"x":38,"y":353,"w":1,"h":1},"rotated":false,"trimmed":false,"spriteSourceSize":{"x":0,"y":0,"w":1,"h":1},"sourceSize":{"w":1,"h":1},"pivot":{"x":0.5,"y":0.5}},"jacket_M_raincoat_h_wav_lc_3499_6_0.png":{"frame":{"x":38,"y":353,"w":1,"h":1},"rotated":false,"trimmed":false,"spriteSourceSize":{"x":0,"y":0,"w":1,"h":1},"sourceSize":{"w":1,"h":1},"pivot":{"x":0.5,"y":0.5}},"jacket_M_raincoat_h_wav_lc_3499_6_1.png":{"frame":{"x":38,"y":353,"w":1,"h":1},"rotated":false,"trimmed":false,"spriteSourceSize":{"x":0,"y":0,"w":1,"h":1},"sourceSize":{"w":1,"h":1},"pivot":{"x":0.5,"y":0.5}},"jacket_M_raincoat_h_wav_lc_3499_7_0.png":{"frame":{"x":38,"y":353,"w":1,"h":1},"rotated":false,"trimmed":false,"spriteSourceSize":{"x":0,"y":0,"w":1,"h":1},"sourceSize":{"w":1,"h":1},"pivot":{"x":0.5,"y":0.5}},"jacket_M_raincoat_h_wav_lc_3499_7_1.png":{"frame":{"x":38,"y":353,"w":1,"h":1},"rotated":false,"trimmed":false,"spriteSourceSize":{"x":0,"y":0,"w":1,"h":1},"sourceSize":{"w":1,"h":1},"pivot":{"x":0.5,"y":0.5}},"jacket_M_raincoat_h_wlk_lc_3499_0_0.png":{"frame":{"x":38,"y":353,"w":1,"h":1},"rotated":false,"trimmed":false,"spriteSourceSize":{"x":0,"y":0,"w":1,"h":1},"sourceSize":{"w":1,"h":1},"pivot":{"x":0.5,"y":0.5}},"jacket_M_raincoat_h_wlk_lc_3499_0_2.png":{"frame":{"x":38,"y":353,"w":1,"h":1},"rotated":false,"trimmed":false,"spriteSourceSize":{"x":0,"y":0,"w":1,"h":1},"sourceSize":{"w":1,"h":1},"pivot":{"x":0.5,"y":0.5}},"jacket_M_raincoat_h_wlk_lc_3499_0_3.png":{"frame":{"x":38,"y":353,"w":1,"h":1},"rotated":false,"trimmed":false,"spriteSourceSize":{"x":0,"y":0,"w":1,"h":1},"sourceSize":{"w":1,"h":1},"pivot":{"x":0.5,"y":0.5}},"jacket_M_raincoat_h_wlk_lc_3499_1_0.png":{"frame":{"x":38,"y":353,"w":1,"h":1},"rotated":false,"trimmed":false,"spriteSourceSize":{"x":0,"y":0,"w":1,"h":1},"sourceSize":{"w":1,"h":1},"pivot":{"x":0.5,"y":0.5}},"jacket_M_raincoat_h_wlk_lc_3499_1_1.png":{"frame":{"x":38,"y":353,"w":1,"h":1},"rotated":false,"trimmed":false,"spriteSourceSize":{"x":0,"y":0,"w":1,"h":1},"sourceSize":{"w":1,"h":1},"pivot":{"x":0.5,"y":0.5}},"jacket_M_raincoat_h_wlk_lc_3499_1_2.png":{"frame":{"x":38,"y":353,"w":1,"h":1},"rotated":false,"trimmed":false,"spriteSourceSize":{"x":0,"y":0,"w":1,"h":1},"sourceSize":{"w":1,"h":1},"pivot":{"x":0.5,"y":0.5}},"jacket_M_raincoat_h_wlk_lc_3499_1_3.png":{"frame":{"x":38,"y":353,"w":1,"h":1},"rotated":false,"trimmed":false,"spriteSourceSize":{"x":0,"y":0,"w":1,"h":1},"sourceSize":{"w":1,"h":1},"pivot":{"x":0.5,"y":0.5}},"jacket_M_raincoat_h_wlk_lc_3499_2_0.png":{"frame":{"x":38,"y":353,"w":1,"h":1},"rotated":false,"trimmed":false,"spriteSourceSize":{"x":0,"y":0,"w":1,"h":1},"sourceSize":{"w":1,"h":1},"pivot":{"x":0.5,"y":0.5}},"jacket_M_raincoat_h_wlk_lc_3499_2_1.png":{"frame":{"x":38,"y":353,"w":1,"h":1},"rotated":false,"trimmed":false,"spriteSourceSize":{"x":0,"y":0,"w":1,"h":1},"sourceSize":{"w":1,"h":1},"pivot":{"x":0.5,"y":0.5}},"jacket_M_raincoat_h_wlk_lc_3499_2_2.png":{"frame":{"x":38,"y":353,"w":1,"h":1},"rotated":false,"trimmed":false,"spriteSourceSize":{"x":0,"y":0,"w":1,"h":1},"sourceSize":{"w":1,"h":1},"pivot":{"x":0.5,"y":0.5}},"jacket_M_raincoat_h_wlk_lc_3499_2_3.png":{"frame":{"x":38,"y":353,"w":1,"h":1},"rotated":false,"trimmed":false,"spriteSourceSize":{"x":0,"y":0,"w":1,"h":1},"sourceSize":{"w":1,"h":1},"pivot":{"x":0.5,"y":0.5}},"jacket_M_raincoat_h_wlk_lc_3499_3_0.png":{"frame":{"x":38,"y":353,"w":1,"h":1},"rotated":false,"trimmed":false,"spriteSourceSize":{"x":0,"y":0,"w":1,"h":1},"sourceSize":{"w":1,"h":1},"pivot":{"x":0.5,"y":0.5}},"jacket_M_raincoat_h_wlk_lc_3499_3_1.png":{"frame":{"x":38,"y":353,"w":1,"h":1},"rotated":false,"trimmed":false,"spriteSourceSize":{"x":0,"y":0,"w":1,"h":1},"sourceSize":{"w":1,"h":1},"pivot":{"x":0.5,"y":0.5}},"jacket_M_raincoat_h_wlk_lc_3499_3_2.png":{"frame":{"x":38,"y":353,"w":1,"h":1},"rotated":false,"trimmed":false,"spriteSourceSize":{"x":0,"y":0,"w":1,"h":1},"sourceSize":{"w":1,"h":1},"pivot":{"x":0.5,"y":0.5}},"jacket_M_raincoat_h_wlk_lc_3499_3_3.png":{"frame":{"x":38,"y":353,"w":1,"h":1},"rotated":false,"trimmed":false,"spriteSourceSize":{"x":0,"y":0,"w":1,"h":1},"sourceSize":{"w":1,"h":1},"pivot":{"x":0.5,"y":0.5}},"jacket_M_raincoat_h_wlk_lc_3499_7_0.png":{"frame":{"x":38,"y":353,"w":1,"h":1},"rotated":false,"trimmed":false,"spriteSourceSize":{"x":0,"y":0,"w":1,"h":1},"sourceSize":{"w":1,"h":1},"pivot":{"x":0.5,"y":0.5}},"jacket_M_raincoat_h_wlk_lc_3499_7_1.png":{"frame":{"x":38,"y":353,"w":1,"h":1},"rotated":false,"trimmed":false,"spriteSourceSize":{"x":0,"y":0,"w":1,"h":1},"sourceSize":{"w":1,"h":1},"pivot":{"x":0.5,"y":0.5}},"jacket_M_raincoat_h_wlk_lc_3499_7_2.png":{"frame":{"x":38,"y":353,"w":1,"h":1},"rotated":false,"trimmed":false,"spriteSourceSize":{"x":0,"y":0,"w":1,"h":1},"sourceSize":{"w":1,"h":1},"pivot":{"x":0.5,"y":0.5}},"jacket_M_raincoat_h_wlk_lc_3499_7_3.png":{"frame":{"x":38,"y":353,"w":1,"h":1},"rotated":false,"trimmed":false,"spriteSourceSize":{"x":0,"y":0,"w":1,"h":1},"sourceSize":{"w":1,"h":1},"pivot":{"x":0.5,"y":0.5}},"jacket_M_raincoat_h_wlk_rc_3499_0_0.png":{"frame":{"x":38,"y":353,"w":1,"h":1},"rotated":false,"trimmed":false,"spriteSourceSize":{"x":0,"y":0,"w":1,"h":1},"sourceSize":{"w":1,"h":1},"pivot":{"x":0.5,"y":0.5}},"jacket_M_raincoat_h_wlk_rc_3499_0_1.png":{"frame":{"x":38,"y":353,"w":1,"h":1},"rotated":false,"trimmed":false,"spriteSourceSize":{"x":0,"y":0,"w":1,"h":1},"sourceSize":{"w":1,"h":1},"pivot":{"x":0.5,"y":0.5}},"jacket_M_raincoat_h_wlk_rc_3499_0_3.png":{"frame":{"x":38,"y":353,"w":1,"h":1},"rotated":false,"trimmed":false,"spriteSourceSize":{"x":0,"y":0,"w":1,"h":1},"sourceSize":{"w":1,"h":1},"pivot":{"x":0.5,"y":0.5}},"jacket_M_raincoat_h_wlk_rc_3499_1_0.png":{"frame":{"x":38,"y":353,"w":1,"h":1},"rotated":false,"trimmed":false,"spriteSourceSize":{"x":0,"y":0,"w":1,"h":1},"sourceSize":{"w":1,"h":1},"pivot":{"x":0.5,"y":0.5}},"jacket_M_raincoat_h_wlk_rc_3499_1_1.png":{"frame":{"x":38,"y":353,"w":1,"h":1},"rotated":false,"trimmed":false,"spriteSourceSize":{"x":0,"y":0,"w":1,"h":1},"sourceSize":{"w":1,"h":1},"pivot":{"x":0.5,"y":0.5}},"jacket_M_raincoat_h_wlk_rc_3499_1_2.png":{"frame":{"x":38,"y":353,"w":1,"h":1},"rotated":false,"trimmed":false,"spriteSourceSize":{"x":0,"y":0,"w":1,"h":1},"sourceSize":{"w":1,"h":1},"pivot":{"x":0.5,"y":0.5}},"jacket_M_raincoat_h_wlk_rc_3499_1_3.png":{"frame":{"x":38,"y":353,"w":1,"h":1},"rotated":false,"trimmed":false,"spriteSourceSize":{"x":0,"y":0,"w":1,"h":1},"sourceSize":{"w":1,"h":1},"pivot":{"x":0.5,"y":0.5}},"jacket_M_raincoat_h_wlk_rc_3499_2_0.png":{"frame":{"x":38,"y":353,"w":1,"h":1},"rotated":false,"trimmed":false,"spriteSourceSize":{"x":0,"y":0,"w":1,"h":1},"sourceSize":{"w":1,"h":1},"pivot":{"x":0.5,"y":0.5}},"jacket_M_raincoat_h_wlk_rc_3499_2_1.png":{"frame":{"x":38,"y":353,"w":1,"h":1},"rotated":false,"trimmed":false,"spriteSourceSize":{"x":0,"y":0,"w":1,"h":1},"sourceSize":{"w":1,"h":1},"pivot":{"x":0.5,"y":0.5}},"jacket_M_raincoat_h_wlk_rc_3499_2_2.png":{"frame":{"x":38,"y":353,"w":1,"h":1},"rotated":false,"trimmed":false,"spriteSourceSize":{"x":0,"y":0,"w":1,"h":1},"sourceSize":{"w":1,"h":1},"pivot":{"x":0.5,"y":0.5}},"jacket_M_raincoat_h_wlk_rc_3499_2_3.png":{"frame":{"x":38,"y":353,"w":1,"h":1},"rotated":false,"trimmed":false,"spriteSourceSize":{"x":0,"y":0,"w":1,"h":1},"sourceSize":{"w":1,"h":1},"pivot":{"x":0.5,"y":0.5}},"jacket_M_raincoat_h_wlk_rc_3499_3_0.png":{"frame":{"x":38,"y":353,"w":1,"h":1},"rotated":false,"trimmed":false,"spriteSourceSize":{"x":0,"y":0,"w":1,"h":1},"sourceSize":{"w":1,"h":1},"pivot":{"x":0.5,"y":0.5}},"jacket_M_raincoat_h_wlk_rc_3499_3_1.png":{"frame":{"x":38,"y":353,"w":1,"h":1},"rotated":false,"trimmed":false,"spriteSourceSize":{"x":0,"y":0,"w":1,"h":1},"sourceSize":{"w":1,"h":1},"pivot":{"x":0.5,"y":0.5}},"jacket_M_raincoat_h_wlk_rc_3499_3_3.png":{"frame":{"x":38,"y":353,"w":1,"h":1},"rotated":false,"trimmed":false,"spriteSourceSize":{"x":0,"y":0,"w":1,"h":1},"sourceSize":{"w":1,"h":1},"pivot":{"x":0.5,"y":0.5}},"jacket_M_raincoat_h_wlk_rc_3499_7_0.png":{"frame":{"x":38,"y":353,"w":1,"h":1},"rotated":false,"trimmed":false,"spriteSourceSize":{"x":0,"y":0,"w":1,"h":1},"sourceSize":{"w":1,"h":1},"pivot":{"x":0.5,"y":0.5}},"jacket_M_raincoat_h_wlk_rc_3499_7_1.png":{"frame":{"x":38,"y":353,"w":1,"h":1},"rotated":false,"trimmed":false,"spriteSourceSize":{"x":0,"y":0,"w":1,"h":1},"sourceSize":{"w":1,"h":1},"pivot":{"x":0.5,"y":0.5}},"jacket_M_raincoat_h_wlk_rc_3499_7_2.png":{"frame":{"x":38,"y":353,"w":1,"h":1},"rotated":false,"trimmed":false,"spriteSourceSize":{"x":0,"y":0,"w":1,"h":1},"sourceSize":{"w":1,"h":1},"pivot":{"x":0.5,"y":0.5}},"jacket_M_raincoat_h_wlk_rc_3499_7_3.png":{"frame":{"x":38,"y":353,"w":1,"h":1},"rotated":false,"trimmed":false,"spriteSourceSize":{"x":0,"y":0,"w":1,"h":1},"sourceSize":{"w":1,"h":1},"pivot":{"x":0.5,"y":0.5}},"jacket_M_raincoat_h_crr_rc_3500_6_0.png":{"frame":{"x":39,"y":353,"w":1,"h":1},"rotated":false,"trimmed":false,"spriteSourceSize":{"x":0,"y":0,"w":1,"h":1},"sourceSize":{"w":1,"h":1},"pivot":{"x":0.5,"y":0.5}},"jacket_M_raincoat_h_std_rc_3499_0_0.png":{"frame":{"x":40,"y":353,"w":1,"h":1},"rotated":false,"trimmed":false,"spriteSourceSize":{"x":0,"y":0,"w":1,"h":1},"sourceSize":{"w":1,"h":1},"pivot":{"x":0.5,"y":0.5}},"jacket_M_raincoat_h_wlk_rc_3499_3_2.png":{"frame":{"x":40,"y":353,"w":1,"h":1},"rotated":false,"trimmed":false,"spriteSourceSize":{"x":0,"y":0,"w":1,"h":1},"sourceSize":{"w":1,"h":1},"pivot":{"x":0.5,"y":0.5}},"jacket_M_raincoat_h_wlk_lc_3498_1_0.png":{"frame":{"x":127,"y":23,"w":9,"h":23},"rotated":false,"trimmed":false,"spriteSourceSize":{"x":0,"y":0,"w":9,"h":23},"sourceSize":{"w":9,"h":23},"pivot":{"x":0.5,"y":0.5}},"jacket_M_raincoat_h_wlk_lc_3498_1_2.png":{"frame":{"x":127,"y":23,"w":9,"h":23},"rotated":false,"trimmed":false,"spriteSourceSize":{"x":0,"y":0,"w":9,"h":23},"sourceSize":{"w":9,"h":23},"pivot":{"x":0.5,"y":0.5}},"jacket_M_raincoat_h_wlk_rc_3498_1_0.png":{"frame":{"x":127,"y":23,"w":9,"h":23},"rotated":false,"trimmed":false,"spriteSourceSize":{"x":0,"y":0,"w":9,"h":23},"sourceSize":{"w":9,"h":23},"pivot":{"x":0.5,"y":0.5}},"jacket_M_raincoat_h_wlk_rc_3498_1_2.png":{"frame":{"x":127,"y":23,"w":9,"h":23},"rotated":false,"trimmed":false,"spriteSourceSize":{"x":0,"y":0,"w":9,"h":23},"sourceSize":{"w":9,"h":23},"pivot":{"x":0.5,"y":0.5}},"jacket_M_raincoat_h_wlk_rc_3498_2_0.png":{"frame":{"x":29,"y":274,"w":17,"h":32},"rotated":false,"trimmed":false,"spriteSourceSize":{"x":0,"y":0,"w":17,"h":32},"sourceSize":{"w":17,"h":32},"pivot":{"x":0.5,"y":0.5}},"jacket_M_raincoat_h_wlk_rc_3498_2_2.png":{"frame":{"x":29,"y":274,"w":17,"h":32},"rotated":false,"trimmed":false,"spriteSourceSize":{"x":0,"y":0,"w":17,"h":32},"sourceSize":{"w":17,"h":32},"pivot":{"x":0.5,"y":0.5}},"jacket_M_raincoat_h_wlk_rc_3498_3_0.png":{"frame":{"x":76,"y":274,"w":10,"h":28},"rotated":false,"trimmed":false,"spriteSourceSize":{"x":0,"y":0,"w":10,"h":28},"sourceSize":{"w":10,"h":28},"pivot":{"x":0.5,"y":0.5}},"jacket_M_raincoat_h_wlk_rc_3498_3_2.png":{"frame":{"x":76,"y":274,"w":10,"h":28},"rotated":false,"trimmed":false,"spriteSourceSize":{"x":0,"y":0,"w":10,"h":28},"sourceSize":{"w":10,"h":28},"pivot":{"x":0.5,"y":0.5}},"jacket_M_raincoat_h_wlk_lc_3499_0_1.png":{"frame":{"x":33,"y":311,"w":1,"h":2},"rotated":false,"trimmed":false,"spriteSourceSize":{"x":0,"y":0,"w":1,"h":2},"sourceSize":{"w":1,"h":2},"pivot":{"x":0.5,"y":0.5}},"jacket_M_raincoat_h_wlk_rc_3499_0_2.png":{"frame":{"x":33,"y":311,"w":1,"h":2},"rotated":false,"trimmed":false,"spriteSourceSize":{"x":0,"y":0,"w":1,"h":2},"sourceSize":{"w":1,"h":2},"pivot":{"x":0.5,"y":0.5}},"jacket_M_raincoat_h_wlk_lc_3498_0_2.png":{"frame":{"x":72,"y":75,"w":9,"h":25},"rotated":false,"trimmed":false,"spriteSourceSize":{"x":0,"y":0,"w":9,"h":25},"sourceSize":{"w":9,"h":25},"pivot":{"x":0.5,"y":0.5}},"jacket_M_raincoat_h_wlk_lc_3498_7_2.png":{"frame":{"x":112,"y":201,"w":9,"h":27},"rotated":false,"trimmed":false,"spriteSourceSize":{"x":0,"y":0,"w":9,"h":27},"sourceSize":{"w":9,"h":27},"pivot":{"x":0.5,"y":0.5}},"jacket_M_raincoat_h_wlk_lc_3500_0_1.png":{"frame":{"x":41,"y":353,"w":1,"h":1},"rotated":false,"trimmed":false,"spriteSourceSize":{"x":0,"y":0,"w":1,"h":1},"sourceSize":{"w":1,"h":1},"pivot":{"x":0.5,"y":0.5}},"jacket_M_raincoat_h_wlk_lc_3500_0_2.png":{"frame":{"x":41,"y":353,"w":1,"h":1},"rotated":false,"trimmed":false,"spriteSourceSize":{"x":0,"y":0,"w":1,"h":1},"sourceSize":{"w":1,"h":1},"pivot":{"x":0.5,"y":0.5}},"jacket_M_raincoat_h_wlk_lc_3500_0_3.png":{"frame":{"x":41,"y":353,"w":1,"h":1},"rotated":false,"trimmed":false,"spriteSourceSize":{"x":0,"y":0,"w":1,"h":1},"sourceSize":{"w":1,"h":1},"pivot":{"x":0.5,"y":0.5}},"jacket_M_raincoat_h_wlk_lc_3500_1_2.png":{"frame":{"x":173,"y":114,"w":6,"h":18},"rotated":false,"trimmed":false,"spriteSourceSize":{"x":0,"y":0,"w":6,"h":18},"sourceSize":{"w":6,"h":18},"pivot":{"x":0.5,"y":0.5}},"jacket_M_raincoat_h_wlk_rc_3500_1_0.png":{"frame":{"x":173,"y":114,"w":6,"h":18},"rotated":false,"trimmed":false,"spriteSourceSize":{"x":0,"y":0,"w":6,"h":18},"sourceSize":{"w":6,"h":18},"pivot":{"x":0.5,"y":0.5}},"jacket_M_raincoat_h_wlk_rc_3500_1_2.png":{"frame":{"x":173,"y":114,"w":6,"h":18},"rotated":false,"trimmed":false,"spriteSourceSize":{"x":0,"y":0,"w":6,"h":18},"sourceSize":{"w":6,"h":18},"pivot":{"x":0.5,"y":0.5}},"jacket_M_raincoat_h_wlk_rc_3500_1_1.png":{"frame":{"x":179,"y":114,"w":6,"h":18},"rotated":false,"trimmed":false,"spriteSourceSize":{"x":0,"y":0,"w":6,"h":18},"sourceSize":{"w":6,"h":18},"pivot":{"x":0.5,"y":0.5}},"jacket_M_raincoat_h_wlk_lc_3500_3_2.png":{"frame":{"x":89,"y":0,"w":8,"h":25},"rotated":false,"trimmed":false,"spriteSourceSize":{"x":0,"y":0,"w":8,"h":25},"sourceSize":{"w":8,"h":25},"pivot":{"x":0.5,"y":0.5}},"jacket_M_raincoat_h_wlk_rc_3500_0_2.png":{"frame":{"x":132,"y":92,"w":9,"h":22},"rotated":false,"trimmed":false,"spriteSourceSize":{"x":0,"y":0,"w":9,"h":22},"sourceSize":{"w":9,"h":22},"pivot":{"x":0.5,"y":0.5}},"jacket_M_raincoat_h_wlk_rc_3500_2_2.png":{"frame":{"x":32,"y":178,"w":16,"h":29},"rotated":false,"trimmed":false,"spriteSourceSize":{"x":0,"y":0,"w":16,"h":29},"sourceSize":{"w":16,"h":29},"pivot":{"x":0.5,"y":0.5}},"jacket_M_raincoat_h_wlk_rc_3500_3_2.png":{"frame":{"x":81,"y":75,"w":8,"h":25},"rotated":false,"trimmed":false,"spriteSourceSize":{"x":0,"y":0,"w":8,"h":25},"sourceSize":{"w":8,"h":25},"pivot":{"x":0.5,"y":0.5}}},"meta":{"app":"http://github.com/odrick/free-tex-packer-core","version":"0.3.2","image":"pack-result.png","format":"RGBA8888","size":{"w":228,"h":494},"scale":1}},"h_std_lc_3498_0_0":{"x":-16,"y":47,"exists":true},"h_std_cc_3498_0_0":{"x":-17,"y":49,"exists":true},"h_std_rc_3498_0_0":{"x":-36,"y":43,"exists":true},"h_std_lc_3498_1_0":{"x":-27,"y":43,"exists":true},"h_std_cc_3498_1_0":{"x":-18,"y":48,"exists":true},"h_std_rc_3498_1_0":{"x":-27,"y":43,"exists":true},"h_std_lc_3498_2_0":{"x":-42,"y":48,"exists":true},"h_std_cc_3498_2_0":{"x":-15,"y":55,"exists":true},"h_std_rc_3498_2_0":{"x":-15,"y":51,"exists":true},"h_std_cc_3498_3_0":{"x":-19,"y":53,"exists":true},"h_std_rc_3498_3_0":{"x":-16,"y":48,"exists":true},"h_std_lc_3498_3_0":{"x":-41,"y":49,"exists":true},"h_std_lc_3498_7_0":{"x":-16,"y":46,"exists":true},"h_std_rc_3498_7_0":{"x":-43,"y":46,"exists":true},"h_std_cc_3498_7_0":{"x":-21,"y":49,"exists":true},"h_std_lc_3499_0_0":{"x":-18,"y":38,"exists":true},"h_std_cc_3499_0_0":{"x":-39,"y":40,"exists":true},"h_std_rc_3499_0_0":{"x":-43,"y":41,"exists":true},"h_std_lc_3499_1_0":{"x":-32,"y":43,"exists":true},"h_std_cc_3499_1_0":{"x":-39,"y":39,"exists":true},"h_std_rc_3499_1_0":{"x":-32,"y":43,"exists":true},"h_std_lc_3499_2_0":{"x":-45,"y":40,"exists":true},"h_std_cc_3499_2_0":{"x":-31,"y":44,"exists":true},"h_std_rc_3499_2_0":{"x":-20,"y":46,"exists":true},"h_std_cc_3499_3_0":{"x":-27,"y":42,"exists":true},"h_std_rc_3499_3_0":{"x":-21,"y":34,"exists":true},"h_std_lc_3499_3_0":{"x":-45,"y":35,"exists":true},"h_std_lc_3499_7_0":{"x":-21,"y":43,"exists":true},"h_std_rc_3499_7_0":{"x":-45,"y":43,"exists":true},"h_std_cc_3499_7_0":{"x":-36,"y":34,"exists":true},"h_std_lc_3500_0_0":{"x":-17,"y":27,"exists":true},"h_std_cc_3500_0_0":{"x":-18,"y":46,"exists":true},"h_std_rc_3500_0_0":{"x":-36,"y":42,"exists":true},"h_std_lc_3500_1_0":{"x":-28,"y":41,"exists":true},"h_std_cc_3500_1_0":{"x":-19,"y":45,"exists":true},"h_std_rc_3500_1_0":{"x":-28,"y":41,"exists":true},"h_std_lc_3500_2_0":{"x":-44,"y":45,"exists":true},"h_std_cc_3500_2_0":{"x":-16,"y":54,"exists":true},"h_std_rc_3500_2_0":{"x":-16,"y":51,"exists":true},"h_std_cc_3500_3_0":{"x":-20,"y":52,"exists":true},"h_std_rc_3500_3_0":{"x":-17,"y":48,"exists":true},"h_std_lc_3500_3_0":{"x":-42,"y":48,"exists":true},"h_std_lc_3500_7_0":{"x":-17,"y":43,"exists":true},"h_std_rc_3500_7_0":{"x":-45,"y":43,"exists":true},"h_std_cc_3500_7_0":{"x":-22,"y":134,"exists":true},"h_wlk_lc_3498_0_0":{"x":-16,"y":47,"exists":true},"h_wlk_lc_3498_0_1":{"x":-16,"y":47,"exists":true},"h_wlk_lc_3498_0_2":{"x":-16,"y":47,"exists":true},"h_wlk_lc_3498_0_3":{"x":-14,"y":47,"exists":true},"h_wlk_rc_3498_0_0":{"x":-36,"y":43,"exists":true},"h_wlk_rc_3498_0_1":{"x":-34,"y":43,"exists":true},"h_wlk_rc_3498_0_2":{"x":-36,"y":44,"exists":true},"h_wlk_rc_3498_0_3":{"x":-36,"y":43,"exists":true},"h_wlk_lc_3498_1_0":{"x":-27,"y":43,"exists":true},"h_wlk_lc_3498_1_1":{"x":-21,"y":43,"exists":true},"h_wlk_lc_3498_1_2":{"x":-27,"y":43,"exists":true},"h_wlk_lc_3498_1_3":{"x":-21,"y":37,"exists":true},"h_wlk_rc_3498_1_0":{"x":-27,"y":43,"exists":true},"h_wlk_rc_3498_1_1":{"x":-21,"y":43,"exists":true},"h_wlk_rc_3498_1_2":{"x":-27,"y":43,"exists":true},"h_wlk_rc_3498_1_3":{"x":-26,"y":43,"exists":true},"h_wlk_lc_3498_2_0":{"x":-42,"y":48,"exists":true},"h_wlk_lc_3498_2_1":{"x":-42,"y":48,"exists":true},"h_wlk_lc_3498_2_2":{"x":-42,"y":48,"exists":true},"h_wlk_lc_3498_2_3":{"x":-42,"y":47,"exists":true},"h_wlk_rc_3498_2_0":{"x":-15,"y":51,"exists":true},"h_wlk_rc_3498_2_1":{"x":-14,"y":51,"exists":true},"h_wlk_rc_3498_2_2":{"x":-15,"y":51,"exists":true},"h_wlk_rc_3498_2_3":{"x":-15,"y":51,"exists":true},"h_wlk_rc_3498_3_0":{"x":-16,"y":48,"exists":true},"h_wlk_rc_3498_3_1":{"x":-16,"y":48,"exists":true},"h_wlk_rc_3498_3_2":{"x":-16,"y":48,"exists":true},"h_wlk_rc_3498_3_3":{"x":-16,"y":48,"exists":true},"h_wlk_lc_3498_3_0":{"x":-41,"y":48,"exists":true},"h_wlk_lc_3498_3_1":{"x":-41,"y":48,"exists":true},"h_wlk_lc_3498_3_2":{"x":-41,"y":49,"exists":true},"h_wlk_lc_3498_3_3":{"x":-41,"y":48,"exists":true},"h_wlk_rc_3498_7_0":{"x":-43,"y":46,"exists":true},"h_wlk_rc_3498_7_1":{"x":-42,"y":46,"exists":true},"h_wlk_rc_3498_7_2":{"x":-42,"y":46,"exists":true},"h_wlk_rc_3498_7_3":{"x":-42,"y":46,"exists":true},"h_wlk_lc_3498_7_0":{"x":-16,"y":46,"exists":true},"h_wlk_lc_3498_7_1":{"x":-16,"y":46,"exists":true},"h_wlk_lc_3498_7_2":{"x":-16,"y":46,"exists":true},"h_wlk_lc_3498_7_3":{"x":-16,"y":46,"exists":true},"h_wlk_lc_3499_0_0":{"x":-24,"y":34,"exists":true},"h_wlk_lc_3499_0_1":{"x":-24,"y":34,"exists":true},"h_wlk_lc_3499_0_2":{"x":-24,"y":34,"exists":true},"h_wlk_lc_3499_0_3":{"x":-24,"y":34,"exists":true},"h_wlk_rc_3499_0_0":{"x":-39,"y":31,"exists":true},"h_wlk_rc_3499_0_1":{"x":-39,"y":30,"exists":true},"h_wlk_rc_3499_0_2":{"x":-39,"y":31,"exists":true},"h_wlk_rc_3499_0_3":{"x":-39,"y":32,"exists":true},"h_wlk_lc_3499_1_0":{"x":-27,"y":35,"exists":true},"h_wlk_lc_3499_1_1":{"x":-27,"y":32,"exists":true},"h_wlk_lc_3499_1_2":{"x":-27,"y":38,"exists":true},"h_wlk_lc_3499_1_3":{"x":-27,"y":38,"exists":true},"h_wlk_rc_3499_1_0":{"x":-27,"y":38,"exists":true},"h_wlk_rc_3499_1_1":{"x":-27,"y":35,"exists":true},"h_wlk_rc_3499_1_2":{"x":-27,"y":36,"exists":true},"h_wlk_rc_3499_1_3":{"x":-27,"y":35,"exists":true},"h_wlk_lc_3499_2_0":{"x":-45,"y":38,"exists":true},"h_wlk_lc_3499_2_1":{"x":-45,"y":38,"exists":true},"h_wlk_lc_3499_2_2":{"x":-45,"y":37,"exists":true},"h_wlk_lc_3499_2_3":{"x":-45,"y":39,"exists":true},"h_wlk_rc_3499_2_0":{"x":-27,"y":35,"exists":true},"h_wlk_rc_3499_2_1":{"x":-27,"y":35,"exists":true},"h_wlk_rc_3499_2_2":{"x":-27,"y":36,"exists":true},"h_wlk_rc_3499_2_3":{"x":-27,"y":37,"exists":true},"h_wlk_rc_3499_3_0":{"x":-23,"y":33,"exists":true},"h_wlk_rc_3499_3_1":{"x":-23,"y":33,"exists":true},"h_wlk_rc_3499_3_2":{"x":-23,"y":34,"exists":true},"h_wlk_rc_3499_3_3":{"x":-23,"y":34,"exists":true},"h_wlk_lc_3499_3_0":{"x":-43,"y":32,"exists":true},"h_wlk_lc_3499_3_1":{"x":-43,"y":32,"exists":true},"h_wlk_lc_3499_3_2":{"x":-43,"y":30,"exists":true},"h_wlk_lc_3499_3_3":{"x":-43,"y":35,"exists":true},"h_wlk_rc_3499_7_0":{"x":-43,"y":32,"exists":true},"h_wlk_rc_3499_7_1":{"x":-43,"y":30,"exists":true},"h_wlk_rc_3499_7_2":{"x":-43,"y":32,"exists":true},"h_wlk_rc_3499_7_3":{"x":-43,"y":32,"exists":true},"h_wlk_lc_3499_7_0":{"x":-23,"y":32,"exists":true},"h_wlk_lc_3499_7_1":{"x":-23,"y":34,"exists":true},"h_wlk_lc_3499_7_2":{"x":-23,"y":34,"exists":true},"h_wlk_lc_3499_7_3":{"x":-23,"y":35,"exists":true},"h_wlk_lc_3500_0_0":{"x":-19,"y":36,"exists":true},"h_wlk_lc_3500_0_1":{"x":-19,"y":36,"exists":true},"h_wlk_lc_3500_0_2":{"x":-19,"y":36,"exists":true},"h_wlk_lc_3500_0_3":{"x":-19,"y":36,"exists":true},"h_wlk_rc_3500_0_0":{"x":-36,"y":42,"exists":true},"h_wlk_rc_3500_0_1":{"x":-36,"y":42,"exists":true},"h_wlk_rc_3500_0_2":{"x":-36,"y":42,"exists":true},"h_wlk_rc_3500_0_3":{"x":-36,"y":42,"exists":true},"h_wlk_lc_3500_1_0":{"x":-28,"y":41,"exists":true},"h_wlk_lc_3500_1_1":{"x":-24,"y":41,"exists":true},"h_wlk_lc_3500_1_2":{"x":-28,"y":41,"exists":true},"h_wlk_lc_3500_1_3":{"x":-24,"y":35,"exists":true},"h_wlk_rc_3500_1_0":{"x":-28,"y":41,"exists":true},"h_wlk_rc_3500_1_1":{"x":-24,"y":41,"exists":true},"h_wlk_rc_3500_1_2":{"x":-28,"y":41,"exists":true},"h_wlk_rc_3500_1_3":{"x":-30,"y":41,"exists":true},"h_wlk_lc_3500_2_0":{"x":-44,"y":45,"exists":true},"h_wlk_lc_3500_2_1":{"x":-44,"y":46,"exists":true},"h_wlk_lc_3500_2_2":{"x":-44,"y":45,"exists":true},"h_wlk_lc_3500_2_3":{"x":-44,"y":46,"exists":true},"h_wlk_rc_3500_2_0":{"x":-16,"y":51,"exists":true},"h_wlk_rc_3500_2_1":{"x":-16,"y":51,"exists":true},"h_wlk_rc_3500_2_2":{"x":-16,"y":51,"exists":true},"h_wlk_rc_3500_2_3":{"x":-16,"y":51,"exists":true},"h_wlk_rc_3500_3_0":{"x":-17,"y":48,"exists":true},"h_wlk_rc_3500_3_1":{"x":-19,"y":48,"exists":true},"h_wlk_rc_3500_3_2":{"x":-17,"y":48,"exists":true},"h_wlk_rc_3500_3_3":{"x":-18,"y":48,"exists":true},"h_wlk_lc_3500_3_0":{"x":-42,"y":48,"exists":true},"h_wlk_lc_3500_3_1":{"x":-42,"y":48,"exists":true},"h_wlk_lc_3500_3_2":{"x":-42,"y":48,"exists":true},"h_wlk_lc_3500_3_3":{"x":-42,"y":48,"exists":true},"h_wlk_rc_3500_7_0":{"x":-43,"y":44,"exists":true},"h_wlk_rc_3500_7_1":{"x":-43,"y":44,"exists":true},"h_wlk_rc_3500_7_2":{"x":-43,"y":44,"exists":true},"h_wlk_rc_3500_7_3":{"x":-43,"y":44,"exists":true},"h_wlk_lc_3500_7_0":{"x":-18,"y":44,"exists":true},"h_wlk_lc_3500_7_1":{"x":-19,"y":44,"exists":true},"h_wlk_lc_3500_7_2":{"x":-18,"y":44,"exists":true},"h_wlk_lc_3500_7_3":{"x":-18,"y":44,"exists":true},"h_wav_lc_3498_0_0":{"x":-11,"y":66,"exists":true},"h_wav_lc_3498_0_1":{"x":-8,"y":65,"exists":true},"h_wav_lc_3498_1_0":{"x":41,"y":68,"exists":true},"h_wav_lc_3498_1_1":{"x":-27,"y":68,"exists":true},"h_wav_lc_3498_2_0":{"x":-39,"y":66,"exists":true},"h_wav_lc_3498_2_1":{"x":-39,"y":65,"exists":true},"h_wav_lc_3498_3_0":{"x":-41,"y":64,"exists":true},"h_wav_lc_3498_3_1":{"x":-41,"y":64,"exists":true},"h_wav_lc_3498_4_0":{"x":-33,"y":62,"exists":true},"h_wav_lc_3498_4_1":{"x":-33,"y":61,"exists":true},"h_wav_lc_3498_5_0":{"x":-21,"y":66,"exists":true},"h_wav_lc_3498_5_1":{"x":-22,"y":65,"exists":true},"h_wav_lc_3498_6_0":{"x":-10,"y":62,"exists":true},"h_wav_lc_3498_6_1":{"x":-7,"y":61,"exists":true},"h_wav_lc_3498_7_0":{"x":-11,"y":64,"exists":true},"h_wav_lc_3498_7_1":{"x":-9,"y":64,"exists":true},"h_wav_lc_3499_0_0":{"x":-24,"y":47,"exists":true},"h_wav_lc_3499_0_1":{"x":-24,"y":47,"exists":true},"h_wav_lc_3499_1_0":{"x":-35,"y":40,"exists":true},"h_wav_lc_3499_1_1":{"x":-35,"y":40,"exists":true},"h_wav_lc_3499_2_0":{"x":-45,"y":40,"exists":true},"h_wav_lc_3499_2_1":{"x":-45,"y":39,"exists":true},"h_wav_lc_3499_3_0":{"x":-45,"y":47,"exists":true},"h_wav_lc_3499_3_1":{"x":-40,"y":42,"exists":true},"h_wav_lc_3499_4_0":{"x":-40,"y":46,"exists":true},"h_wav_lc_3499_4_1":{"x":-40,"y":46,"exists":true},"h_wav_lc_3499_5_0":{"x":-29,"y":39,"exists":true},"h_wav_lc_3499_5_1":{"x":-29,"y":39,"exists":true},"h_wav_lc_3499_6_0":{"x":-25,"y":34,"exists":true},"h_wav_lc_3499_6_1":{"x":-25,"y":34,"exists":true},"h_wav_lc_3499_7_0":{"x":-21,"y":36,"exists":true},"h_wav_lc_3499_7_1":{"x":-21,"y":38,"exists":true},"h_wav_lc_3500_0_0":{"x":-13,"y":64,"exists":true},"h_wav_lc_3500_0_1":{"x":-10,"y":63,"exists":true},"h_wav_lc_3500_1_0":{"x":-30,"y":61,"exists":true},"h_wav_lc_3500_1_1":{"x":-30,"y":61,"exists":true},"h_wav_lc_3500_2_0":{"x":-41,"y":65,"exists":true},"h_wav_lc_3500_2_1":{"x":-41,"y":58,"exists":true},"h_wav_lc_3500_3_0":{"x":-42,"y":62,"exists":true},"h_wav_lc_3500_3_1":{"x":-42,"y":62,"exists":true},"h_wav_lc_3500_4_0":{"x":-35,"y":61,"exists":true},"h_wav_lc_3500_4_1":{"x":-35,"y":60,"exists":true},"h_wav_lc_3500_5_0":{"x":-22,"y":65,"exists":true},"h_wav_lc_3500_5_1":{"x":-23,"y":64,"exists":true},"h_wav_lc_3500_6_0":{"x":-12,"y":61,"exists":true},"h_wav_lc_3500_6_1":{"x":-9,"y":60,"exists":true},"h_wav_lc_3500_7_0":{"x":-13,"y":62,"exists":true},"h_wav_lc_3500_7_1":{"x":-11,"y":62,"exists":true},"h_lay_lc_3498_2_0":{"x":-12,"y":25,"exists":true},"h_lay_cc_3498_2_0":{"x":15,"y":25,"exists":true},"h_lay_rc_3498_2_0":{"x":9,"y":15,"exists":true},"h_lay_lc_3499_2_0":{"x":-16,"y":23,"exists":true},"h_lay_cc_3499_2_0":{"x":-3,"y":22,"exists":true},"h_lay_rc_3499_2_0":{"x":0,"y":7,"exists":true},"h_lay_lc_3500_2_0":{"x":-16,"y":22,"exists":true},"h_lay_cc_3500_2_0":{"x":13,"y":24,"exists":true},"h_lay_rc_3500_2_0":{"x":1,"y":12,"exists":true},"h_drk_rc_3498_0_0":{"x":-35,"y":52,"exists":true},"h_drk_rc_3498_1_0":{"x":-26,"y":48,"exists":true},"h_drk_rc_3498_2_0":{"x":-15,"y":51,"exists":true},"h_drk_rc_3498_3_0":{"x":-16,"y":50,"exists":true},"h_drk_rc_3498_4_0":{"x":-10,"y":48,"exists":true},"h_drk_rc_3498_5_0":{"x":-8,"y":49,"exists":true},"h_drk_rc_3498_6_0":{"x":-20,"y":50,"exists":true},"h_drk_rc_3498_7_0":{"x":-40,"y":49,"exists":true},"h_drk_rc_3499_0_0":{"x":-43,"y":41,"exists":true},"h_drk_rc_3499_1_0":{"x":-35,"y":40,"exists":true},"h_drk_rc_3499_2_0":{"x":-26,"y":38,"exists":true},"h_drk_rc_3499_3_0":{"x":-23,"y":35,"exists":true},"h_drk_rc_3499_4_0":{"x":-23,"y":37,"exists":true},"h_drk_rc_3499_5_0":{"x":-27,"y":37,"exists":true},"h_drk_rc_3499_6_0":{"x":-46,"y":46,"exists":true},"h_drk_rc_3499_7_0":{"x":-46,"y":46,"exists":true},"h_drk_rc_3500_0_0":{"x":-36,"y":51,"exists":true},"h_drk_rc_3500_1_0":{"x":-28,"y":47,"exists":true},"h_drk_rc_3500_2_0":{"x":-16,"y":51,"exists":true},"h_drk_rc_3500_3_0":{"x":-19,"y":49,"exists":true},"h_drk_rc_3500_4_0":{"x":-12,"y":47,"exists":true},"h_drk_rc_3500_5_0":{"x":-9,"y":48,"exists":true},"h_drk_rc_3500_6_0":{"x":-22,"y":49,"exists":true},"h_drk_rc_3500_7_0":{"x":-40,"y":44,"exists":true},"h_crr_lc_3498_7_0":{"x":-16,"y":47,"exists":true},"h_crr_rc_3498_7_0":{"x":-42,"y":47,"exists":true},"h_crr_rc_3498_6_0":{"x":-44,"y":49,"exists":true},"h_crr_lc_3498_6_0":{"x":-12,"y":43,"exists":true},"h_crr_rc_3498_5_0":{"x":-22,"y":45,"exists":true},"h_crr_lc_3498_5_0":{"x":-22,"y":43,"exists":true},"h_crr_rc_3498_4_0":{"x":-12,"y":50,"exists":true},"h_crr_lc_3498_4_0":{"x":-31,"y":51,"exists":true},"h_crr_rc_3498_3_0":{"x":-16,"y":48,"exists":true},"h_crr_lc_3498_3_0":{"x":-39,"y":48,"exists":true},"h_crr_lc_3498_2_0":{"x":-42,"y":49,"exists":true},"h_crr_rc_3498_2_0":{"x":-15,"y":51,"exists":true},"h_crr_lc_3498_1_0":{"x":-26,"y":45,"exists":true},"h_crr_rc_3498_1_0":{"x":-26,"y":43,"exists":true},"h_crr_lc_3498_0_0":{"x":-17,"y":49,"exists":true},"h_crr_rc_3498_0_0":{"x":-23,"y":44,"exists":true},"h_crr_lc_3499_7_0":{"x":-21,"y":35,"exists":true},"h_crr_rc_3499_7_0":{"x":-45,"y":36,"exists":true},"h_crr_rc_3499_6_0":{"x":-46,"y":37,"exists":true},"h_crr_lc_3499_6_0":{"x":-28,"y":36,"exists":true},"h_crr_rc_3499_5_0":{"x":-39,"y":38,"exists":true},"h_crr_lc_3499_5_0":{"x":-39,"y":39,"exists":true},"h_crr_rc_3499_4_0":{"x":-23,"y":37,"exists":true},"h_crr_lc_3499_4_0":{"x":-44,"y":40,"exists":true},"h_crr_rc_3499_3_0":{"x":-23,"y":36,"exists":true},"h_crr_lc_3499_3_0":{"x":-43,"y":35,"exists":true},"h_crr_lc_3499_2_0":{"x":-45,"y":38,"exists":true},"h_crr_rc_3499_2_0":{"x":-26,"y":35,"exists":true},"h_crr_lc_3499_1_0":{"x":-35,"y":37,"exists":true},"h_crr_rc_3499_1_0":{"x":-35,"y":39,"exists":true},"h_crr_lc_3499_0_0":{"x":-19,"y":37,"exists":true},"h_crr_rc_3499_0_0":{"x":-39,"y":31,"exists":true},"h_crr_lc_3500_7_0":{"x":-18,"y":43,"exists":true},"h_crr_rc_3500_7_0":{"x":-47,"y":43,"exists":true},"h_crr_rc_3500_6_0":{"x":-44,"y":43,"exists":true},"h_crr_lc_3500_6_0":{"x":-14,"y":42,"exists":true},"h_crr_rc_3500_5_0":{"x":-23,"y":44,"exists":true},"h_crr_lc_3500_5_0":{"x":-23,"y":42,"exists":true},"h_crr_rc_3500_4_0":{"x":-14,"y":46,"exists":true},"h_crr_lc_3500_4_0":{"x":-33,"y":40,"exists":true},"h_crr_rc_3500_3_0":{"x":-19,"y":48,"exists":true},"h_crr_lc_3500_3_0":{"x":-42,"y":48,"exists":true},"h_crr_lc_3500_2_0":{"x":-45,"y":45,"exists":true},"h_crr_rc_3500_2_0":{"x":-16,"y":51,"exists":true},"h_crr_lc_3500_1_0":{"x":-29,"y":44,"exists":true},"h_crr_rc_3500_1_0":{"x":-29,"y":42,"exists":true},"h_crr_lc_3500_0_0":{"x":-22,"y":43,"exists":true},"h_crr_rc_3500_0_0":{"x":-36,"y":42,"exists":true}}