{"atlas":{"frames":{"trousers_U_bikinibottomstars_h_sit_lg_2224_0_0.png":{"frame":{"x":0,"y":0,"w":24,"h":16},"rotated":false,"trimmed":false,"spriteSourceSize":{"x":0,"y":0,"w":24,"h":16},"sourceSize":{"w":24,"h":16},"pivot":{"x":0.5,"y":0.5}},"trousers_U_bikinibottomstars_h_sit_lg_2224_2_0.png":{"frame":{"x":24,"y":0,"w":24,"h":16},"rotated":false,"trimmed":false,"spriteSourceSize":{"x":0,"y":0,"w":24,"h":16},"sourceSize":{"w":24,"h":16},"pivot":{"x":0.5,"y":0.5}},"trousers_U_bikinibottomstars_h_std_lg_2224_2_0.png":{"frame":{"x":48,"y":0,"w":22,"h":13},"rotated":false,"trimmed":false,"spriteSourceSize":{"x":0,"y":0,"w":22,"h":13},"sourceSize":{"w":22,"h":13},"pivot":{"x":0.5,"y":0.5}},"trousers_U_bikinibottomstars_h_wlk_lg_2224_0_1.png":{"frame":{"x":70,"y":0,"w":22,"h":13},"rotated":false,"trimmed":false,"spriteSourceSize":{"x":0,"y":0,"w":22,"h":13},"sourceSize":{"w":22,"h":13},"pivot":{"x":0.5,"y":0.5}},"trousers_U_bikinibottomstars_h_wlk_lg_2224_0_3.png":{"frame":{"x":92,"y":0,"w":22,"h":13},"rotated":false,"trimmed":false,"spriteSourceSize":{"x":0,"y":0,"w":22,"h":13},"sourceSize":{"w":22,"h":13},"pivot":{"x":0.5,"y":0.5}},"trousers_U_bikinibottomstars_h_sit_lg_2225_2_0.png":{"frame":{"x":114,"y":0,"w":22,"h":10},"rotated":false,"trimmed":false,"spriteSourceSize":{"x":0,"y":0,"w":22,"h":10},"sourceSize":{"w":22,"h":10},"pivot":{"x":0.5,"y":0.5}},"trousers_U_bikinibottomstars_h_lay_lg_2224_2_0.png":{"frame":{"x":136,"y":0,"w":21,"h":17},"rotated":false,"trimmed":false,"spriteSourceSize":{"x":0,"y":0,"w":21,"h":17},"sourceSize":{"w":21,"h":17},"pivot":{"x":0.5,"y":0.5}},"trousers_U_bikinibottomstars_h_std_lg_2224_0_0.png":{"frame":{"x":114,"y":10,"w":21,"h":13},"rotated":false,"trimmed":false,"spriteSourceSize":{"x":0,"y":0,"w":21,"h":13},"sourceSize":{"w":21,"h":13},"pivot":{"x":0.5,"y":0.5}},"trousers_U_bikinibottomstars_h_wlk_lg_2224_2_3.png":{"frame":{"x":48,"y":13,"w":21,"h":13},"rotated":false,"trimmed":false,"spriteSourceSize":{"x":0,"y":0,"w":21,"h":13},"sourceSize":{"w":21,"h":13},"pivot":{"x":0.5,"y":0.5}},"trousers_U_bikinibottomstars_h_sit_lg_2225_0_0.png":{"frame":{"x":69,"y":13,"w":21,"h":8},"rotated":false,"trimmed":false,"spriteSourceSize":{"x":0,"y":0,"w":21,"h":8},"sourceSize":{"w":21,"h":8},"pivot":{"x":0.5,"y":0.5}},"trousers_U_bikinibottomstars_h_std_lg_2224_3_0.png":{"frame":{"x":90,"y":13,"w":21,"h":8},"rotated":false,"trimmed":false,"spriteSourceSize":{"x":0,"y":0,"w":21,"h":8},"sourceSize":{"w":21,"h":8},"pivot":{"x":0.5,"y":0.5}},"trousers_U_bikinibottomstars_h_std_lg_2224_7_0.png":{"frame":{"x":69,"y":21,"w":21,"h":8},"rotated":false,"trimmed":false,"spriteSourceSize":{"x":0,"y":0,"w":21,"h":8},"sourceSize":{"w":21,"h":8},"pivot":{"x":0.5,"y":0.5}},"trousers_U_bikinibottomstars_h_wlk_lg_2224_3_0.png":{"frame":{"x":90,"y":21,"w":21,"h":8},"rotated":false,"trimmed":false,"spriteSourceSize":{"x":0,"y":0,"w":21,"h":8},"sourceSize":{"w":21,"h":8},"pivot":{"x":0.5,"y":0.5}},"trousers_U_bikinibottomstars_h_wlk_lg_2224_3_1.png":{"frame":{"x":0,"y":16,"w":21,"h":8},"rotated":false,"trimmed":false,"spriteSourceSize":{"x":0,"y":0,"w":21,"h":8},"sourceSize":{"w":21,"h":8},"pivot":{"x":0.5,"y":0.5}},"trousers_U_bikinibottomstars_h_wlk_lg_2224_3_2.png":{"frame":{"x":21,"y":16,"w":21,"h":8},"rotated":false,"trimmed":false,"spriteSourceSize":{"x":0,"y":0,"w":21,"h":8},"sourceSize":{"w":21,"h":8},"pivot":{"x":0.5,"y":0.5}},"trousers_U_bikinibottomstars_sh_std_lg_2225_1_0.png":{"frame":{"x":42,"y":16,"w":5,"h":3},"rotated":false,"trimmed":false,"spriteSourceSize":{"x":0,"y":0,"w":5,"h":3},"sourceSize":{"w":5,"h":3},"pivot":{"x":0.5,"y":0.5}},"trousers_U_bikinibottomstars_h_wlk_lg_2224_3_3.png":{"frame":{"x":0,"y":24,"w":21,"h":8},"rotated":false,"trimmed":false,"spriteSourceSize":{"x":0,"y":0,"w":21,"h":8},"sourceSize":{"w":21,"h":8},"pivot":{"x":0.5,"y":0.5}},"trousers_U_bikinibottomstars_h_wlk_lg_2224_7_0.png":{"frame":{"x":21,"y":24,"w":21,"h":8},"rotated":false,"trimmed":false,"spriteSourceSize":{"x":0,"y":0,"w":21,"h":8},"sourceSize":{"w":21,"h":8},"pivot":{"x":0.5,"y":0.5}},"trousers_U_bikinibottomstars_h_wlk_lg_2224_7_1.png":{"frame":{"x":42,"y":26,"w":21,"h":8},"rotated":false,"trimmed":false,"spriteSourceSize":{"x":0,"y":0,"w":21,"h":8},"sourceSize":{"w":21,"h":8},"pivot":{"x":0.5,"y":0.5}},"trousers_U_bikinibottomstars_h_wlk_lg_2224_7_2.png":{"frame":{"x":0,"y":32,"w":21,"h":8},"rotated":false,"trimmed":false,"spriteSourceSize":{"x":0,"y":0,"w":21,"h":8},"sourceSize":{"w":21,"h":8},"pivot":{"x":0.5,"y":0.5}},"trousers_U_bikinibottomstars_h_wlk_lg_2224_7_3.png":{"frame":{"x":21,"y":32,"w":21,"h":8},"rotated":false,"trimmed":false,"spriteSourceSize":{"x":0,"y":0,"w":21,"h":8},"sourceSize":{"w":21,"h":8},"pivot":{"x":0.5,"y":0.5}},"trousers_U_bikinibottomstars_h_wlk_lg_2224_2_0.png":{"frame":{"x":157,"y":0,"w":20,"h":13},"rotated":false,"trimmed":false,"spriteSourceSize":{"x":0,"y":0,"w":20,"h":13},"sourceSize":{"w":20,"h":13},"pivot":{"x":0.5,"y":0.5}},"trousers_U_bikinibottomstars_h_lay_lg_2225_2_0.png":{"frame":{"x":177,"y":0,"w":18,"h":12},"rotated":false,"trimmed":false,"spriteSourceSize":{"x":0,"y":0,"w":18,"h":12},"sourceSize":{"w":18,"h":12},"pivot":{"x":0.5,"y":0.5}},"trousers_U_bikinibottomstars_h_std_lg_2225_2_0.png":{"frame":{"x":195,"y":0,"w":18,"h":10},"rotated":false,"trimmed":false,"spriteSourceSize":{"x":0,"y":0,"w":18,"h":10},"sourceSize":{"w":18,"h":10},"pivot":{"x":0.5,"y":0.5}},"trousers_U_bikinibottomstars_h_wlk_lg_2225_2_0.png":{"frame":{"x":213,"y":0,"w":18,"h":10},"rotated":false,"trimmed":false,"spriteSourceSize":{"x":0,"y":0,"w":18,"h":10},"sourceSize":{"w":18,"h":10},"pivot":{"x":0.5,"y":0.5}},"trousers_U_bikinibottomstars_h_std_lg_2225_0_0.png":{"frame":{"x":231,"y":0,"w":18,"h":8},"rotated":false,"trimmed":false,"spriteSourceSize":{"x":0,"y":0,"w":18,"h":8},"sourceSize":{"w":18,"h":8},"pivot":{"x":0.5,"y":0.5}},"trousers_U_bikinibottomstars_h_wlk_lg_2225_0_1.png":{"frame":{"x":249,"y":0,"w":18,"h":8},"rotated":false,"trimmed":false,"spriteSourceSize":{"x":0,"y":0,"w":18,"h":8},"sourceSize":{"w":18,"h":8},"pivot":{"x":0.5,"y":0.5}},"trousers_U_bikinibottomstars_h_wlk_lg_2224_1_1.png":{"frame":{"x":267,"y":0,"w":16,"h":8},"rotated":false,"trimmed":false,"spriteSourceSize":{"x":0,"y":0,"w":16,"h":8},"sourceSize":{"w":16,"h":8},"pivot":{"x":0.5,"y":0.5}},"trousers_U_bikinibottomstars_h_wlk_lg_2224_1_3.png":{"frame":{"x":283,"y":0,"w":16,"h":8},"rotated":false,"trimmed":false,"spriteSourceSize":{"x":0,"y":0,"w":16,"h":8},"sourceSize":{"w":16,"h":8},"pivot":{"x":0.5,"y":0.5}},"trousers_U_bikinibottomstars_h_std_lg_2224_1_0.png":{"frame":{"x":299,"y":0,"w":16,"h":7},"rotated":false,"trimmed":false,"spriteSourceSize":{"x":0,"y":0,"w":16,"h":7},"sourceSize":{"w":16,"h":7},"pivot":{"x":0.5,"y":0.5}},"trousers_U_bikinibottomstars_h_wlk_lg_2224_1_0.png":{"frame":{"x":315,"y":0,"w":16,"h":7},"rotated":false,"trimmed":false,"spriteSourceSize":{"x":0,"y":0,"w":16,"h":7},"sourceSize":{"w":16,"h":7},"pivot":{"x":0.5,"y":0.5}},"trousers_U_bikinibottomstars_h_std_lg_2225_3_0.png":{"frame":{"x":331,"y":0,"w":16,"h":6},"rotated":false,"trimmed":false,"spriteSourceSize":{"x":0,"y":0,"w":16,"h":6},"sourceSize":{"w":16,"h":6},"pivot":{"x":0.5,"y":0.5}},"trousers_U_bikinibottomstars_sh_sit_lg_2224_2_0.png":{"frame":{"x":347,"y":0,"w":13,"h":7},"rotated":false,"trimmed":false,"spriteSourceSize":{"x":0,"y":0,"w":13,"h":7},"sourceSize":{"w":13,"h":7},"pivot":{"x":0.5,"y":0.5}},"trousers_U_bikinibottomstars_sh_std_lg_2224_3_0.png":{"frame":{"x":331,"y":6,"w":13,"h":5},"rotated":false,"trimmed":false,"spriteSourceSize":{"x":0,"y":0,"w":13,"h":5},"sourceSize":{"w":13,"h":5},"pivot":{"x":0.5,"y":0.5}},"trousers_U_bikinibottomstars_sh_wlk_lg_2224_3_0.png":{"frame":{"x":299,"y":7,"w":13,"h":5},"rotated":false,"trimmed":false,"spriteSourceSize":{"x":0,"y":0,"w":13,"h":5},"sourceSize":{"w":13,"h":5},"pivot":{"x":0.5,"y":0.5}},"trousers_U_bikinibottomstars_sh_wlk_lg_2224_3_1.png":{"frame":{"x":312,"y":7,"w":13,"h":5},"rotated":false,"trimmed":false,"spriteSourceSize":{"x":0,"y":0,"w":13,"h":5},"sourceSize":{"w":13,"h":5},"pivot":{"x":0.5,"y":0.5}},"trousers_U_bikinibottomstars_sh_wlk_lg_2224_3_2.png":{"frame":{"x":231,"y":8,"w":13,"h":5},"rotated":false,"trimmed":false,"spriteSourceSize":{"x":0,"y":0,"w":13,"h":5},"sourceSize":{"w":13,"h":5},"pivot":{"x":0.5,"y":0.5}},"trousers_U_bikinibottomstars_sh_wlk_lg_2224_3_3.png":{"frame":{"x":195,"y":10,"w":13,"h":5},"rotated":false,"trimmed":false,"spriteSourceSize":{"x":0,"y":0,"w":13,"h":5},"sourceSize":{"w":13,"h":5},"pivot":{"x":0.5,"y":0.5}},"trousers_U_bikinibottomstars_sh_lay_lg_2224_2_0.png":{"frame":{"x":177,"y":12,"w":12,"h":9},"rotated":false,"trimmed":false,"spriteSourceSize":{"x":0,"y":0,"w":12,"h":9},"sourceSize":{"w":12,"h":9},"pivot":{"x":0.5,"y":0.5}},"trousers_U_bikinibottomstars_sh_sit_lg_2224_0_0.png":{"frame":{"x":157,"y":15,"w":12,"h":7},"rotated":false,"trimmed":false,"spriteSourceSize":{"x":0,"y":0,"w":12,"h":7},"sourceSize":{"w":12,"h":7},"pivot":{"x":0.5,"y":0.5}},"trousers_U_bikinibottomstars_sh_std_lg_2224_1_0.png":{"frame":{"x":169,"y":15,"w":8,"h":5},"rotated":false,"trimmed":false,"spriteSourceSize":{"x":0,"y":0,"w":8,"h":5},"sourceSize":{"w":8,"h":5},"pivot":{"x":0.5,"y":0.5}},"trousers_U_bikinibottomstars_sh_std_lg_2225_0_0.png":{"frame":{"x":169,"y":20,"w":7,"h":4},"rotated":false,"trimmed":false,"spriteSourceSize":{"x":0,"y":0,"w":7,"h":4},"sourceSize":{"w":7,"h":4},"pivot":{"x":0.5,"y":0.5}},"trousers_U_bikinibottomstars_h_std_lg_2225_7_0.png":{"frame":{"x":135,"y":17,"w":12,"h":6},"rotated":false,"trimmed":false,"spriteSourceSize":{"x":0,"y":0,"w":12,"h":6},"sourceSize":{"w":12,"h":6},"pivot":{"x":0.5,"y":0.5}},"trousers_U_bikinibottomstars_sh_lay_lg_2225_2_0.png":{"frame":{"x":147,"y":17,"w":10,"h":5},"rotated":false,"trimmed":false,"spriteSourceSize":{"x":0,"y":0,"w":10,"h":5},"sourceSize":{"w":10,"h":5},"pivot":{"x":0.5,"y":0.5}},"trousers_U_bikinibottomstars_h_wlk_lg_2225_1_3.png":{"frame":{"x":147,"y":22,"w":12,"h":6},"rotated":false,"trimmed":false,"spriteSourceSize":{"x":0,"y":0,"w":12,"h":6},"sourceSize":{"w":12,"h":6},"pivot":{"x":0.5,"y":0.5}},"trousers_U_bikinibottomstars_sh_sit_lg_2225_2_0.png":{"frame":{"x":159,"y":22,"w":10,"h":5},"rotated":false,"trimmed":false,"spriteSourceSize":{"x":0,"y":0,"w":10,"h":5},"sourceSize":{"w":10,"h":5},"pivot":{"x":0.5,"y":0.5}},"trousers_U_bikinibottomstars_h_std_lg_2225_1_0.png":{"frame":{"x":208,"y":10,"w":12,"h":5},"rotated":false,"trimmed":false,"spriteSourceSize":{"x":0,"y":0,"w":12,"h":5},"sourceSize":{"w":12,"h":5},"pivot":{"x":0.5,"y":0.5}},"trousers_U_bikinibottomstars_sh_std_lg_2224_0_0.png":{"frame":{"x":220,"y":10,"w":11,"h":7},"rotated":false,"trimmed":false,"spriteSourceSize":{"x":0,"y":0,"w":11,"h":7},"sourceSize":{"w":11,"h":7},"pivot":{"x":0.5,"y":0.5}},"trousers_U_bikinibottomstars_sh_std_lg_2224_2_0.png":{"frame":{"x":189,"y":15,"w":11,"h":7},"rotated":false,"trimmed":false,"spriteSourceSize":{"x":0,"y":0,"w":11,"h":7},"sourceSize":{"w":11,"h":7},"pivot":{"x":0.5,"y":0.5}},"trousers_U_bikinibottomstars_sh_wlk_lg_2224_2_0.png":{"frame":{"x":176,"y":21,"w":11,"h":7},"rotated":false,"trimmed":false,"spriteSourceSize":{"x":0,"y":0,"w":11,"h":7},"sourceSize":{"w":11,"h":7},"pivot":{"x":0.5,"y":0.5}},"trousers_U_bikinibottomstars_sh_std_lg_2225_2_0.png":{"frame":{"x":169,"y":24,"w":7,"h":4},"rotated":false,"trimmed":false,"spriteSourceSize":{"x":0,"y":0,"w":7,"h":4},"sourceSize":{"w":7,"h":4},"pivot":{"x":0.5,"y":0.5}},"trousers_U_bikinibottomstars_sh_std_lg_2225_7_0.png":{"frame":{"x":159,"y":27,"w":10,"h":3},"rotated":false,"trimmed":false,"spriteSourceSize":{"x":0,"y":0,"w":10,"h":3},"sourceSize":{"w":10,"h":3},"pivot":{"x":0.5,"y":0.5}},"trousers_U_bikinibottomstars_sh_wlk_lg_2224_1_1.png":{"frame":{"x":200,"y":15,"w":9,"h":5},"rotated":false,"trimmed":false,"spriteSourceSize":{"x":0,"y":0,"w":9,"h":5},"sourceSize":{"w":9,"h":5},"pivot":{"x":0.5,"y":0.5}},"trousers_U_bikinibottomstars_sh_wlk_lg_2224_1_3.png":{"frame":{"x":209,"y":15,"w":9,"h":5},"rotated":false,"trimmed":false,"spriteSourceSize":{"x":0,"y":0,"w":9,"h":5},"sourceSize":{"w":9,"h":5},"pivot":{"x":0.5,"y":0.5}},"trousers_U_bikinibottomstars_sh_sit_lg_2225_0_0.png":{"frame":{"x":111,"y":23,"w":9,"h":4},"rotated":false,"trimmed":false,"spriteSourceSize":{"x":0,"y":0,"w":9,"h":4},"sourceSize":{"w":9,"h":4},"pivot":{"x":0.5,"y":0.5}},"trousers_U_bikinibottomstars_sh_std_lg_2225_3_0.png":{"frame":{"x":120,"y":23,"w":9,"h":3},"rotated":false,"trimmed":false,"spriteSourceSize":{"x":0,"y":0,"w":9,"h":3},"sourceSize":{"w":9,"h":3},"pivot":{"x":0.5,"y":0.5}},"trousers_U_bikinibottomstars_h_wlk_lg_2224_0_0.png":{"frame":{"x":114,"y":10,"w":21,"h":13},"rotated":false,"trimmed":false,"spriteSourceSize":{"x":0,"y":0,"w":21,"h":13},"sourceSize":{"w":21,"h":13},"pivot":{"x":0.5,"y":0.5}},"trousers_U_bikinibottomstars_h_wlk_lg_2224_0_2.png":{"frame":{"x":114,"y":10,"w":21,"h":13},"rotated":false,"trimmed":false,"spriteSourceSize":{"x":0,"y":0,"w":21,"h":13},"sourceSize":{"w":21,"h":13},"pivot":{"x":0.5,"y":0.5}},"trousers_U_bikinibottomstars_h_wlk_lg_2225_0_0.png":{"frame":{"x":231,"y":0,"w":18,"h":8},"rotated":false,"trimmed":false,"spriteSourceSize":{"x":0,"y":0,"w":18,"h":8},"sourceSize":{"w":18,"h":8},"pivot":{"x":0.5,"y":0.5}},"trousers_U_bikinibottomstars_h_wlk_lg_2225_0_2.png":{"frame":{"x":231,"y":0,"w":18,"h":8},"rotated":false,"trimmed":false,"spriteSourceSize":{"x":0,"y":0,"w":18,"h":8},"sourceSize":{"w":18,"h":8},"pivot":{"x":0.5,"y":0.5}},"trousers_U_bikinibottomstars_h_wlk_lg_2225_0_3.png":{"frame":{"x":231,"y":0,"w":18,"h":8},"rotated":false,"trimmed":false,"spriteSourceSize":{"x":0,"y":0,"w":18,"h":8},"sourceSize":{"w":18,"h":8},"pivot":{"x":0.5,"y":0.5}},"trousers_U_bikinibottomstars_h_wlk_lg_2225_1_0.png":{"frame":{"x":208,"y":10,"w":12,"h":5},"rotated":false,"trimmed":false,"spriteSourceSize":{"x":0,"y":0,"w":12,"h":5},"sourceSize":{"w":12,"h":5},"pivot":{"x":0.5,"y":0.5}},"trousers_U_bikinibottomstars_h_wlk_lg_2225_1_1.png":{"frame":{"x":208,"y":10,"w":12,"h":5},"rotated":false,"trimmed":false,"spriteSourceSize":{"x":0,"y":0,"w":12,"h":5},"sourceSize":{"w":12,"h":5},"pivot":{"x":0.5,"y":0.5}},"trousers_U_bikinibottomstars_h_wlk_lg_2225_1_2.png":{"frame":{"x":208,"y":10,"w":12,"h":5},"rotated":false,"trimmed":false,"spriteSourceSize":{"x":0,"y":0,"w":12,"h":5},"sourceSize":{"w":12,"h":5},"pivot":{"x":0.5,"y":0.5}},"trousers_U_bikinibottomstars_h_wlk_lg_2225_2_1.png":{"frame":{"x":195,"y":0,"w":18,"h":10},"rotated":false,"trimmed":false,"spriteSourceSize":{"x":0,"y":0,"w":18,"h":10},"sourceSize":{"w":18,"h":10},"pivot":{"x":0.5,"y":0.5}},"trousers_U_bikinibottomstars_h_wlk_lg_2225_2_2.png":{"frame":{"x":195,"y":0,"w":18,"h":10},"rotated":false,"trimmed":false,"spriteSourceSize":{"x":0,"y":0,"w":18,"h":10},"sourceSize":{"w":18,"h":10},"pivot":{"x":0.5,"y":0.5}},"trousers_U_bikinibottomstars_h_wlk_lg_2225_2_3.png":{"frame":{"x":195,"y":0,"w":18,"h":10},"rotated":false,"trimmed":false,"spriteSourceSize":{"x":0,"y":0,"w":18,"h":10},"sourceSize":{"w":18,"h":10},"pivot":{"x":0.5,"y":0.5}},"trousers_U_bikinibottomstars_h_wlk_lg_2225_3_0.png":{"frame":{"x":331,"y":0,"w":16,"h":6},"rotated":false,"trimmed":false,"spriteSourceSize":{"x":0,"y":0,"w":16,"h":6},"sourceSize":{"w":16,"h":6},"pivot":{"x":0.5,"y":0.5}},"trousers_U_bikinibottomstars_h_wlk_lg_2225_3_1.png":{"frame":{"x":331,"y":0,"w":16,"h":6},"rotated":false,"trimmed":false,"spriteSourceSize":{"x":0,"y":0,"w":16,"h":6},"sourceSize":{"w":16,"h":6},"pivot":{"x":0.5,"y":0.5}},"trousers_U_bikinibottomstars_h_wlk_lg_2225_3_2.png":{"frame":{"x":331,"y":0,"w":16,"h":6},"rotated":false,"trimmed":false,"spriteSourceSize":{"x":0,"y":0,"w":16,"h":6},"sourceSize":{"w":16,"h":6},"pivot":{"x":0.5,"y":0.5}},"trousers_U_bikinibottomstars_h_wlk_lg_2225_3_3.png":{"frame":{"x":331,"y":0,"w":16,"h":6},"rotated":false,"trimmed":false,"spriteSourceSize":{"x":0,"y":0,"w":16,"h":6},"sourceSize":{"w":16,"h":6},"pivot":{"x":0.5,"y":0.5}},"trousers_U_bikinibottomstars_h_wlk_lg_2225_7_0.png":{"frame":{"x":135,"y":17,"w":12,"h":6},"rotated":false,"trimmed":false,"spriteSourceSize":{"x":0,"y":0,"w":12,"h":6},"sourceSize":{"w":12,"h":6},"pivot":{"x":0.5,"y":0.5}},"trousers_U_bikinibottomstars_h_wlk_lg_2225_7_1.png":{"frame":{"x":135,"y":17,"w":12,"h":6},"rotated":false,"trimmed":false,"spriteSourceSize":{"x":0,"y":0,"w":12,"h":6},"sourceSize":{"w":12,"h":6},"pivot":{"x":0.5,"y":0.5}},"trousers_U_bikinibottomstars_h_wlk_lg_2225_7_2.png":{"frame":{"x":135,"y":17,"w":12,"h":6},"rotated":false,"trimmed":false,"spriteSourceSize":{"x":0,"y":0,"w":12,"h":6},"sourceSize":{"w":12,"h":6},"pivot":{"x":0.5,"y":0.5}},"trousers_U_bikinibottomstars_h_wlk_lg_2225_7_3.png":{"frame":{"x":135,"y":17,"w":12,"h":6},"rotated":false,"trimmed":false,"spriteSourceSize":{"x":0,"y":0,"w":12,"h":6},"sourceSize":{"w":12,"h":6},"pivot":{"x":0.5,"y":0.5}},"trousers_U_bikinibottomstars_h_wlk_lg_2224_1_2.png":{"frame":{"x":315,"y":0,"w":16,"h":7},"rotated":false,"trimmed":false,"spriteSourceSize":{"x":0,"y":0,"w":16,"h":7},"sourceSize":{"w":16,"h":7},"pivot":{"x":0.5,"y":0.5}},"trousers_U_bikinibottomstars_h_wlk_lg_2224_2_1.png":{"frame":{"x":157,"y":0,"w":20,"h":13},"rotated":false,"trimmed":false,"spriteSourceSize":{"x":0,"y":0,"w":20,"h":13},"sourceSize":{"w":20,"h":13},"pivot":{"x":0.5,"y":0.5}},"trousers_U_bikinibottomstars_h_wlk_lg_2224_2_2.png":{"frame":{"x":157,"y":0,"w":20,"h":13},"rotated":false,"trimmed":false,"spriteSourceSize":{"x":0,"y":0,"w":20,"h":13},"sourceSize":{"w":20,"h":13},"pivot":{"x":0.5,"y":0.5}},"trousers_U_bikinibottomstars_sh_wlk_lg_2224_0_0.png":{"frame":{"x":220,"y":10,"w":11,"h":7},"rotated":false,"trimmed":false,"spriteSourceSize":{"x":0,"y":0,"w":11,"h":7},"sourceSize":{"w":11,"h":7},"pivot":{"x":0.5,"y":0.5}},"trousers_U_bikinibottomstars_sh_wlk_lg_2224_0_1.png":{"frame":{"x":220,"y":10,"w":11,"h":7},"rotated":false,"trimmed":false,"spriteSourceSize":{"x":0,"y":0,"w":11,"h":7},"sourceSize":{"w":11,"h":7},"pivot":{"x":0.5,"y":0.5}},"trousers_U_bikinibottomstars_sh_wlk_lg_2224_0_2.png":{"frame":{"x":220,"y":10,"w":11,"h":7},"rotated":false,"trimmed":false,"spriteSourceSize":{"x":0,"y":0,"w":11,"h":7},"sourceSize":{"w":11,"h":7},"pivot":{"x":0.5,"y":0.5}},"trousers_U_bikinibottomstars_sh_wlk_lg_2224_0_3.png":{"frame":{"x":220,"y":10,"w":11,"h":7},"rotated":false,"trimmed":false,"spriteSourceSize":{"x":0,"y":0,"w":11,"h":7},"sourceSize":{"w":11,"h":7},"pivot":{"x":0.5,"y":0.5}},"trousers_U_bikinibottomstars_sh_wlk_lg_2224_1_0.png":{"frame":{"x":169,"y":15,"w":8,"h":5},"rotated":false,"trimmed":false,"spriteSourceSize":{"x":0,"y":0,"w":8,"h":5},"sourceSize":{"w":8,"h":5},"pivot":{"x":0.5,"y":0.5}},"trousers_U_bikinibottomstars_sh_wlk_lg_2224_1_2.png":{"frame":{"x":169,"y":15,"w":8,"h":5},"rotated":false,"trimmed":false,"spriteSourceSize":{"x":0,"y":0,"w":8,"h":5},"sourceSize":{"w":8,"h":5},"pivot":{"x":0.5,"y":0.5}},"trousers_U_bikinibottomstars_sh_std_lg_2224_7_0.png":{"frame":{"x":331,"y":6,"w":13,"h":5},"rotated":false,"trimmed":false,"spriteSourceSize":{"x":0,"y":0,"w":13,"h":5},"sourceSize":{"w":13,"h":5},"pivot":{"x":0.5,"y":0.5}},"trousers_U_bikinibottomstars_sh_wlk_lg_2225_0_0.png":{"frame":{"x":169,"y":20,"w":7,"h":4},"rotated":false,"trimmed":false,"spriteSourceSize":{"x":0,"y":0,"w":7,"h":4},"sourceSize":{"w":7,"h":4},"pivot":{"x":0.5,"y":0.5}},"trousers_U_bikinibottomstars_sh_wlk_lg_2225_0_1.png":{"frame":{"x":169,"y":20,"w":7,"h":4},"rotated":false,"trimmed":false,"spriteSourceSize":{"x":0,"y":0,"w":7,"h":4},"sourceSize":{"w":7,"h":4},"pivot":{"x":0.5,"y":0.5}},"trousers_U_bikinibottomstars_sh_wlk_lg_2225_0_2.png":{"frame":{"x":169,"y":20,"w":7,"h":4},"rotated":false,"trimmed":false,"spriteSourceSize":{"x":0,"y":0,"w":7,"h":4},"sourceSize":{"w":7,"h":4},"pivot":{"x":0.5,"y":0.5}},"trousers_U_bikinibottomstars_sh_wlk_lg_2225_0_3.png":{"frame":{"x":169,"y":20,"w":7,"h":4},"rotated":false,"trimmed":false,"spriteSourceSize":{"x":0,"y":0,"w":7,"h":4},"sourceSize":{"w":7,"h":4},"pivot":{"x":0.5,"y":0.5}},"trousers_U_bikinibottomstars_sh_wlk_lg_2225_1_0.png":{"frame":{"x":42,"y":16,"w":5,"h":3},"rotated":false,"trimmed":false,"spriteSourceSize":{"x":0,"y":0,"w":5,"h":3},"sourceSize":{"w":5,"h":3},"pivot":{"x":0.5,"y":0.5}},"trousers_U_bikinibottomstars_sh_wlk_lg_2225_1_1.png":{"frame":{"x":42,"y":16,"w":5,"h":3},"rotated":false,"trimmed":false,"spriteSourceSize":{"x":0,"y":0,"w":5,"h":3},"sourceSize":{"w":5,"h":3},"pivot":{"x":0.5,"y":0.5}},"trousers_U_bikinibottomstars_sh_wlk_lg_2225_1_2.png":{"frame":{"x":42,"y":16,"w":5,"h":3},"rotated":false,"trimmed":false,"spriteSourceSize":{"x":0,"y":0,"w":5,"h":3},"sourceSize":{"w":5,"h":3},"pivot":{"x":0.5,"y":0.5}},"trousers_U_bikinibottomstars_sh_wlk_lg_2225_1_3.png":{"frame":{"x":42,"y":16,"w":5,"h":3},"rotated":false,"trimmed":false,"spriteSourceSize":{"x":0,"y":0,"w":5,"h":3},"sourceSize":{"w":5,"h":3},"pivot":{"x":0.5,"y":0.5}},"trousers_U_bikinibottomstars_sh_wlk_lg_2225_2_0.png":{"frame":{"x":169,"y":24,"w":7,"h":4},"rotated":false,"trimmed":false,"spriteSourceSize":{"x":0,"y":0,"w":7,"h":4},"sourceSize":{"w":7,"h":4},"pivot":{"x":0.5,"y":0.5}},"trousers_U_bikinibottomstars_sh_wlk_lg_2225_2_1.png":{"frame":{"x":169,"y":24,"w":7,"h":4},"rotated":false,"trimmed":false,"spriteSourceSize":{"x":0,"y":0,"w":7,"h":4},"sourceSize":{"w":7,"h":4},"pivot":{"x":0.5,"y":0.5}},"trousers_U_bikinibottomstars_sh_wlk_lg_2225_2_2.png":{"frame":{"x":169,"y":24,"w":7,"h":4},"rotated":false,"trimmed":false,"spriteSourceSize":{"x":0,"y":0,"w":7,"h":4},"sourceSize":{"w":7,"h":4},"pivot":{"x":0.5,"y":0.5}},"trousers_U_bikinibottomstars_sh_wlk_lg_2225_2_3.png":{"frame":{"x":169,"y":24,"w":7,"h":4},"rotated":false,"trimmed":false,"spriteSourceSize":{"x":0,"y":0,"w":7,"h":4},"sourceSize":{"w":7,"h":4},"pivot":{"x":0.5,"y":0.5}},"trousers_U_bikinibottomstars_sh_wlk_lg_2225_3_0.png":{"frame":{"x":120,"y":23,"w":9,"h":3},"rotated":false,"trimmed":false,"spriteSourceSize":{"x":0,"y":0,"w":9,"h":3},"sourceSize":{"w":9,"h":3},"pivot":{"x":0.5,"y":0.5}},"trousers_U_bikinibottomstars_sh_wlk_lg_2225_3_1.png":{"frame":{"x":120,"y":23,"w":9,"h":3},"rotated":false,"trimmed":false,"spriteSourceSize":{"x":0,"y":0,"w":9,"h":3},"sourceSize":{"w":9,"h":3},"pivot":{"x":0.5,"y":0.5}},"trousers_U_bikinibottomstars_sh_wlk_lg_2225_3_2.png":{"frame":{"x":120,"y":23,"w":9,"h":3},"rotated":false,"trimmed":false,"spriteSourceSize":{"x":0,"y":0,"w":9,"h":3},"sourceSize":{"w":9,"h":3},"pivot":{"x":0.5,"y":0.5}},"trousers_U_bikinibottomstars_sh_wlk_lg_2225_3_3.png":{"frame":{"x":120,"y":23,"w":9,"h":3},"rotated":false,"trimmed":false,"spriteSourceSize":{"x":0,"y":0,"w":9,"h":3},"sourceSize":{"w":9,"h":3},"pivot":{"x":0.5,"y":0.5}},"trousers_U_bikinibottomstars_sh_wlk_lg_2225_7_0.png":{"frame":{"x":159,"y":27,"w":10,"h":3},"rotated":false,"trimmed":false,"spriteSourceSize":{"x":0,"y":0,"w":10,"h":3},"sourceSize":{"w":10,"h":3},"pivot":{"x":0.5,"y":0.5}},"trousers_U_bikinibottomstars_sh_wlk_lg_2225_7_1.png":{"frame":{"x":159,"y":27,"w":10,"h":3},"rotated":false,"trimmed":false,"spriteSourceSize":{"x":0,"y":0,"w":10,"h":3},"sourceSize":{"w":10,"h":3},"pivot":{"x":0.5,"y":0.5}},"trousers_U_bikinibottomstars_sh_wlk_lg_2225_7_2.png":{"frame":{"x":159,"y":27,"w":10,"h":3},"rotated":false,"trimmed":false,"spriteSourceSize":{"x":0,"y":0,"w":10,"h":3},"sourceSize":{"w":10,"h":3},"pivot":{"x":0.5,"y":0.5}},"trousers_U_bikinibottomstars_sh_wlk_lg_2225_7_3.png":{"frame":{"x":159,"y":27,"w":10,"h":3},"rotated":false,"trimmed":false,"spriteSourceSize":{"x":0,"y":0,"w":10,"h":3},"sourceSize":{"w":10,"h":3},"pivot":{"x":0.5,"y":0.5}},"trousers_U_bikinibottomstars_sh_wlk_lg_2224_2_1.png":{"frame":{"x":176,"y":21,"w":11,"h":7},"rotated":false,"trimmed":false,"spriteSourceSize":{"x":0,"y":0,"w":11,"h":7},"sourceSize":{"w":11,"h":7},"pivot":{"x":0.5,"y":0.5}},"trousers_U_bikinibottomstars_sh_wlk_lg_2224_2_2.png":{"frame":{"x":176,"y":21,"w":11,"h":7},"rotated":false,"trimmed":false,"spriteSourceSize":{"x":0,"y":0,"w":11,"h":7},"sourceSize":{"w":11,"h":7},"pivot":{"x":0.5,"y":0.5}},"trousers_U_bikinibottomstars_sh_wlk_lg_2224_2_3.png":{"frame":{"x":176,"y":21,"w":11,"h":7},"rotated":false,"trimmed":false,"spriteSourceSize":{"x":0,"y":0,"w":11,"h":7},"sourceSize":{"w":11,"h":7},"pivot":{"x":0.5,"y":0.5}},"trousers_U_bikinibottomstars_sh_wlk_lg_2224_7_0.png":{"frame":{"x":299,"y":7,"w":13,"h":5},"rotated":false,"trimmed":false,"spriteSourceSize":{"x":0,"y":0,"w":13,"h":5},"sourceSize":{"w":13,"h":5},"pivot":{"x":0.5,"y":0.5}},"trousers_U_bikinibottomstars_sh_wlk_lg_2224_7_1.png":{"frame":{"x":312,"y":7,"w":13,"h":5},"rotated":false,"trimmed":false,"spriteSourceSize":{"x":0,"y":0,"w":13,"h":5},"sourceSize":{"w":13,"h":5},"pivot":{"x":0.5,"y":0.5}},"trousers_U_bikinibottomstars_sh_wlk_lg_2224_7_2.png":{"frame":{"x":231,"y":8,"w":13,"h":5},"rotated":false,"trimmed":false,"spriteSourceSize":{"x":0,"y":0,"w":13,"h":5},"sourceSize":{"w":13,"h":5},"pivot":{"x":0.5,"y":0.5}},"trousers_U_bikinibottomstars_sh_wlk_lg_2224_7_3.png":{"frame":{"x":195,"y":10,"w":13,"h":5},"rotated":false,"trimmed":false,"spriteSourceSize":{"x":0,"y":0,"w":13,"h":5},"sourceSize":{"w":13,"h":5},"pivot":{"x":0.5,"y":0.5}}},"meta":{"app":"http://github.com/odrick/free-tex-packer-core","version":"0.3.2","image":"pack-result.png","format":"RGBA8888","size":{"w":360,"h":40},"scale":1}},"h_wlk_lg_2224_0_0":{"x":-21,"y":24,"exists":true},"h_wlk_lg_2224_0_1":{"x":-21,"y":24,"exists":true},"h_wlk_lg_2224_0_2":{"x":-21,"y":24,"exists":true},"h_wlk_lg_2224_0_3":{"x":-21,"y":24,"exists":true},"h_wlk_lg_2224_1_0":{"x":-24,"y":22,"exists":true},"h_wlk_lg_2224_1_1":{"x":-24,"y":22,"exists":true},"h_wlk_lg_2224_1_2":{"x":-24,"y":22,"exists":true},"h_wlk_lg_2224_1_3":{"x":-24,"y":22,"exists":true},"h_wlk_lg_2224_2_0":{"x":-24,"y":26,"exists":true},"h_wlk_lg_2224_2_1":{"x":-24,"y":26,"exists":true},"h_wlk_lg_2224_2_2":{"x":-24,"y":26,"exists":true},"h_wlk_lg_2224_2_3":{"x":-23,"y":26,"exists":true},"h_wlk_lg_2224_3_0":{"x":-23,"y":21,"exists":true},"h_wlk_lg_2224_3_1":{"x":-23,"y":21,"exists":true},"h_wlk_lg_2224_3_2":{"x":-23,"y":21,"exists":true},"h_wlk_lg_2224_3_3":{"x":-23,"y":21,"exists":true},"h_wlk_lg_2224_7_0":{"x":-23,"y":19,"exists":true},"h_wlk_lg_2224_7_1":{"x":-23,"y":19,"exists":true},"h_wlk_lg_2224_7_2":{"x":-23,"y":19,"exists":true},"h_wlk_lg_2224_7_3":{"x":-23,"y":19,"exists":true},"h_wlk_lg_2225_0_0":{"x":-23,"y":20,"exists":true},"h_wlk_lg_2225_0_1":{"x":-23,"y":20,"exists":true},"h_wlk_lg_2225_0_2":{"x":-23,"y":20,"exists":true},"h_wlk_lg_2225_0_3":{"x":-23,"y":20,"exists":true},"h_wlk_lg_2225_1_0":{"x":-27,"y":21,"exists":true},"h_wlk_lg_2225_1_1":{"x":-27,"y":21,"exists":true},"h_wlk_lg_2225_1_2":{"x":-27,"y":21,"exists":true},"h_wlk_lg_2225_1_3":{"x":-27,"y":21,"exists":true},"h_wlk_lg_2225_2_0":{"x":-25,"y":24,"exists":true},"h_wlk_lg_2225_2_1":{"x":-25,"y":24,"exists":true},"h_wlk_lg_2225_2_2":{"x":-25,"y":24,"exists":true},"h_wlk_lg_2225_2_3":{"x":-25,"y":24,"exists":true},"h_wlk_lg_2225_3_0":{"x":-26,"y":20,"exists":true},"h_wlk_lg_2225_3_1":{"x":-26,"y":20,"exists":true},"h_wlk_lg_2225_3_2":{"x":-26,"y":20,"exists":true},"h_wlk_lg_2225_3_3":{"x":-26,"y":20,"exists":true},"h_wlk_lg_2225_7_0":{"x":-28,"y":18,"exists":true},"h_wlk_lg_2225_7_1":{"x":-28,"y":18,"exists":true},"h_wlk_lg_2225_7_2":{"x":-28,"y":18,"exists":true},"h_wlk_lg_2225_7_3":{"x":-28,"y":18,"exists":true},"h_std_lg_2224_0_0":{"x":-21,"y":24,"exists":true},"h_std_lg_2224_1_0":{"x":-24,"y":22,"exists":true},"h_std_lg_2224_2_0":{"x":-22,"y":26,"exists":true},"h_std_lg_2224_3_0":{"x":-23,"y":21,"exists":true},"h_std_lg_2224_7_0":{"x":-23,"y":20,"exists":true},"h_std_lg_2225_0_0":{"x":-23,"y":20,"exists":true},"h_std_lg_2225_1_0":{"x":-27,"y":21,"exists":true},"h_std_lg_2225_2_0":{"x":-25,"y":24,"exists":true},"h_std_lg_2225_3_0":{"x":-26,"y":20,"exists":true},"h_std_lg_2225_7_0":{"x":-28,"y":19,"exists":true},"h_sit_lg_2224_0_0":{"x":-21,"y":26,"exists":true},"h_sit_lg_2224_2_0":{"x":-22,"y":25,"exists":true},"h_sit_lg_2225_0_0":{"x":-23,"y":20,"exists":true},"h_sit_lg_2225_2_0":{"x":-23,"y":24,"exists":true},"h_lay_lg_2224_2_0":{"x":-17,"y":13,"exists":true},"h_lay_lg_2225_2_0":{"x":-18,"y":11,"exists":true},"sh_wlk_lg_2224_0_0":{"x":-10,"y":12,"exists":true},"sh_wlk_lg_2224_0_1":{"x":-10,"y":12,"exists":true},"sh_wlk_lg_2224_0_2":{"x":-10,"y":12,"exists":true},"sh_wlk_lg_2224_0_3":{"x":-10,"y":12,"exists":true},"sh_wlk_lg_2224_1_0":{"x":-12,"y":11,"exists":true},"sh_wlk_lg_2224_1_1":{"x":-11,"y":11,"exists":true},"sh_wlk_lg_2224_1_2":{"x":-12,"y":11,"exists":true},"sh_wlk_lg_2224_1_3":{"x":-11,"y":11,"exists":true},"sh_wlk_lg_2224_2_0":{"x":-10,"y":13,"exists":true},"sh_wlk_lg_2224_2_1":{"x":-10,"y":13,"exists":true},"sh_wlk_lg_2224_2_2":{"x":-10,"y":13,"exists":true},"sh_wlk_lg_2224_2_3":{"x":-10,"y":13,"exists":true},"sh_wlk_lg_2224_3_0":{"x":-9,"y":10,"exists":true},"sh_wlk_lg_2224_3_1":{"x":-9,"y":10,"exists":true},"sh_wlk_lg_2224_3_2":{"x":-9,"y":10,"exists":true},"sh_wlk_lg_2224_3_3":{"x":-9,"y":10,"exists":true},"sh_wlk_lg_2224_7_0":{"x":-10,"y":10,"exists":true},"sh_wlk_lg_2224_7_1":{"x":-10,"y":10,"exists":true},"sh_wlk_lg_2224_7_2":{"x":-10,"y":10,"exists":true},"sh_wlk_lg_2224_7_3":{"x":-10,"y":10,"exists":true},"sh_wlk_lg_2225_0_0":{"x":-12,"y":10,"exists":true},"sh_wlk_lg_2225_0_1":{"x":-12,"y":10,"exists":true},"sh_wlk_lg_2225_0_2":{"x":-12,"y":10,"exists":true},"sh_wlk_lg_2225_0_3":{"x":-12,"y":10,"exists":true},"sh_wlk_lg_2225_1_0":{"x":-14,"y":10,"exists":true},"sh_wlk_lg_2225_1_1":{"x":-14,"y":10,"exists":true},"sh_wlk_lg_2225_1_2":{"x":-14,"y":10,"exists":true},"sh_wlk_lg_2225_1_3":{"x":-14,"y":10,"exists":true},"sh_wlk_lg_2225_2_0":{"x":-12,"y":11,"exists":true},"sh_wlk_lg_2225_2_1":{"x":-12,"y":11,"exists":true},"sh_wlk_lg_2225_2_2":{"x":-12,"y":11,"exists":true},"sh_wlk_lg_2225_2_3":{"x":-12,"y":11,"exists":true},"sh_wlk_lg_2225_3_0":{"x":-11,"y":9,"exists":true},"sh_wlk_lg_2225_3_1":{"x":-11,"y":9,"exists":true},"sh_wlk_lg_2225_3_2":{"x":-11,"y":9,"exists":true},"sh_wlk_lg_2225_3_3":{"x":-11,"y":9,"exists":true},"sh_wlk_lg_2225_7_0":{"x":-12,"y":9,"exists":true},"sh_wlk_lg_2225_7_1":{"x":-12,"y":9,"exists":true},"sh_wlk_lg_2225_7_2":{"x":-12,"y":9,"exists":true},"sh_wlk_lg_2225_7_3":{"x":-12,"y":9,"exists":true},"sh_std_lg_2224_0_0":{"x":-10,"y":12,"exists":true},"sh_std_lg_2224_1_0":{"x":-12,"y":11,"exists":true},"sh_std_lg_2224_2_0":{"x":-10,"y":13,"exists":true},"sh_std_lg_2224_3_0":{"x":-9,"y":10,"exists":true},"sh_std_lg_2224_7_0":{"x":-10,"y":10,"exists":true},"sh_std_lg_2225_0_0":{"x":-12,"y":10,"exists":true},"sh_std_lg_2225_1_0":{"x":-14,"y":10,"exists":true},"sh_std_lg_2225_2_0":{"x":-12,"y":11,"exists":true},"sh_std_lg_2225_3_0":{"x":-11,"y":9,"exists":true},"sh_std_lg_2225_7_0":{"x":-12,"y":9,"exists":true},"sh_sit_lg_2224_0_0":{"x":-11,"y":13,"exists":true},"sh_sit_lg_2224_2_0":{"x":-8,"y":14,"exists":true},"sh_sit_lg_2225_0_0":{"x":-13,"y":11,"exists":true},"sh_sit_lg_2225_2_0":{"x":-10,"y":13,"exists":true},"sh_lay_lg_2224_2_0":{"x":-7,"y":7,"exists":true},"sh_lay_lg_2225_2_0":{"x":-8,"y":5,"exists":true}}