{"atlas":{"frames":{"acc_head_U_earring_x_h_std_he_2116_3_0.png":{"frame":{"x":0,"y":0,"w":30,"h":8},"rotated":false,"trimmed":false,"spriteSourceSize":{"x":0,"y":0,"w":30,"h":8},"sourceSize":{"w":30,"h":8},"pivot":{"x":0.5,"y":0.5}},"acc_head_U_earring_x_h_std_he_2116_7_0.png":{"frame":{"x":30,"y":0,"w":28,"h":8},"rotated":false,"trimmed":false,"spriteSourceSize":{"x":0,"y":0,"w":28,"h":8},"sourceSize":{"w":28,"h":8},"pivot":{"x":0.5,"y":0.5}},"acc_head_U_earring_x_h_std_he_2116_2_0.png":{"frame":{"x":58,"y":0,"w":26,"h":15},"rotated":false,"trimmed":false,"spriteSourceSize":{"x":0,"y":0,"w":26,"h":15},"sourceSize":{"w":26,"h":15},"pivot":{"x":0.5,"y":0.5}},"acc_head_U_earring_x_sh_std_he_2116_3_0.png":{"frame":{"x":0,"y":8,"w":17,"h":5},"rotated":false,"trimmed":false,"spriteSourceSize":{"x":0,"y":0,"w":17,"h":5},"sourceSize":{"w":17,"h":5},"pivot":{"x":0.5,"y":0.5}},"acc_head_U_earring_x_h_std_he_2116_0_0.png":{"frame":{"x":17,"y":8,"w":7,"h":9},"rotated":false,"trimmed":false,"spriteSourceSize":{"x":0,"y":0,"w":7,"h":9},"sourceSize":{"w":7,"h":9},"pivot":{"x":0.5,"y":0.5}},"acc_head_U_earring_x_h_lay_he_2116_2_0.png":{"frame":{"x":0,"y":13,"w":7,"h":8},"rotated":false,"trimmed":false,"spriteSourceSize":{"x":0,"y":0,"w":7,"h":8},"sourceSize":{"w":7,"h":8},"pivot":{"x":0.5,"y":0.5}},"acc_head_U_earring_x_sh_lay_he_2116_2_0.png":{"frame":{"x":7,"y":13,"w":5,"h":5},"rotated":false,"trimmed":false,"spriteSourceSize":{"x":0,"y":0,"w":5,"h":5},"sourceSize":{"w":5,"h":5},"pivot":{"x":0.5,"y":0.5}},"acc_head_U_earring_x_sh_std_he_2116_0_0.png":{"frame":{"x":12,"y":13,"w":5,"h":5},"rotated":false,"trimmed":false,"spriteSourceSize":{"x":0,"y":0,"w":5,"h":5},"sourceSize":{"w":5,"h":5},"pivot":{"x":0.5,"y":0.5}},"acc_head_U_earring_x_sh_std_he_2116_2_0.png":{"frame":{"x":24,"y":8,"w":5,"h":5},"rotated":false,"trimmed":false,"spriteSourceSize":{"x":0,"y":0,"w":5,"h":5},"sourceSize":{"w":5,"h":5},"pivot":{"x":0.5,"y":0.5}},"acc_head_U_earring_x_h_std_he_2116_1_0.png":{"frame":{"x":0,"y":13,"w":7,"h":8},"rotated":false,"trimmed":false,"spriteSourceSize":{"x":0,"y":0,"w":7,"h":8},"sourceSize":{"w":7,"h":8},"pivot":{"x":0.5,"y":0.5}},"acc_head_U_earring_x_sh_std_he_2116_1_0.png":{"frame":{"x":7,"y":13,"w":5,"h":5},"rotated":false,"trimmed":false,"spriteSourceSize":{"x":0,"y":0,"w":5,"h":5},"sourceSize":{"w":5,"h":5},"pivot":{"x":0.5,"y":0.5}},"acc_head_U_earring_x_sh_std_he_2116_7_0.png":{"frame":{"x":0,"y":8,"w":17,"h":5},"rotated":false,"trimmed":false,"spriteSourceSize":{"x":0,"y":0,"w":17,"h":5},"sourceSize":{"w":17,"h":5},"pivot":{"x":0.5,"y":0.5}}},"meta":{"app":"http://github.com/odrick/free-tex-packer-core","version":"0.3.2","image":"pack-result.png","format":"RGBA8888","size":{"w":84,"h":21},"scale":1}},"h_std_he_2116_0_0":{"x":-35,"y":54,"exists":true},"h_std_he_2116_1_0":{"x":-25,"y":54,"exists":true},"h_std_he_2116_2_0":{"x":-21,"y":61,"exists":true},"h_std_he_2116_3_0":{"x":-18,"y":56,"exists":true},"h_std_he_2116_7_0":{"x":-19,"y":54,"exists":true},"h_lay_he_2116_2_0":{"x":12,"y":18,"exists":true},"sh_std_he_2116_0_0":{"x":-17,"y":28,"exists":true},"sh_std_he_2116_1_0":{"x":-11,"y":28,"exists":true},"sh_std_he_2116_2_0":{"x":-9,"y":27,"exists":true},"sh_std_he_2116_3_0":{"x":-7,"y":29,"exists":true},"sh_std_he_2116_7_0":{"x":-8,"y":29,"exists":true},"sh_lay_he_2116_2_0":{"x":5,"y":9,"exists":true}}